Workbook

Sheet Resumo Anual
A1: RESUMO ANUAL — FLUXO DE CAIXA — LOTEAMENTO PAPAGAIOS/MG
A2: INDICADOR | B2: ANO 1 | C2: ANO 2 | D2: ANO 3 | E2: ANO 4 | F2: TOTAL 4 ANOS
A3: Lotes vendidos | B3: =SUMIF(Cronograma!$B$4:Cronograma!$B$51,1,Cronograma!$D$4:Cronograma!$D$51) | C3: =SUMIF(Cronograma!$B$4:Cronograma!$B$51,2,Cronograma!$D$4:Cronograma!$D$51) | D3: =SUMIF(Cronograma!$B$4:Cronograma!$B$51,3,Cronograma!$D$4:Cronograma!$D$51) | E3: =SUMIF(Cronograma!$B$4:Cronograma!$B$51,4,Cronograma!$D$4:Cronograma!$D$51) | F3: =B3+C3+D3+E3
A4: Receita à vista | B4: =SUMIF(Cronograma!$B$4:Cronograma!$B$51,1,Cronograma!$G$4:Cronograma!$G$51) | C4: =SUMIF(Cronograma!$B$4:Cronograma!$B$51,2,Cronograma!$G$4:Cronograma!$G$51) | D4: =SUMIF(Cronograma!$B$4:Cronograma!$B$51,3,Cronograma!$G$4:Cronograma!$G$51) | E4: =SUMIF(Cronograma!$B$4:Cronograma!$B$51,4,Cronograma!$G$4:Cronograma!$G$51) | F4: =B4+C4+D4+E4
A5: Parcelas recebidas | B5: =SUMIF(Cronograma!$B$4:Cronograma!$B$51,1,Cronograma!$H$4:Cronograma!$H$51) | C5: =SUMIF(Cronograma!$B$4:Cronograma!$B$51,2,Cronograma!$H$4:Cronograma!$H$51) | D5: =SUMIF(Cronograma!$B$4:Cronograma!$B$51,3,Cronograma!$H$4:Cronograma!$H$51) | E5: =SUMIF(Cronograma!$B$4:Cronograma!$B$51,4,Cronograma!$H$4:Cronograma!$H$51) | F5: =B5+C5+D5+E5
A6: TOTAL RECEITA | B6: =SUMIF(Cronograma!$B$4:Cronograma!$B$51,1,Cronograma!$I$4:Cronograma!$I$51) | C6: =SUMIF(Cronograma!$B$4:Cronograma!$B$51,2,Cronograma!$I$4:Cronograma!$I$51) | D6: =SUMIF(Cronograma!$B$4:Cronograma!$B$51,3,Cronograma!$I$4:Cronograma!$I$51) | E6: =SUMIF(Cronograma!$B$4:Cronograma!$B$51,4,Cronograma!$I$4:Cronograma!$I$51) | F6: =B6+C6+D6+E6
A7: (-) Infraestrutura | B7: =SUMIF(Cronograma!$B$4:Cronograma!$B$51,1,Cronograma!$E$4:Cronograma!$E$51) | C7: =SUMIF(Cronograma!$B$4:Cronograma!$B$51,2,Cronograma!$E$4:Cronograma!$E$51) | D7: =SUMIF(Cronograma!$B$4:Cronograma!$B$51,3,Cronograma!$E$4:Cronograma!$E$51) | E7: =SUMIF(Cronograma!$B$4:Cronograma!$B$51,4,Cronograma!$E$4:Cronograma!$E$51) | F7: =B7+C7+D7+E7
A8: (-) Corretagem | B8: =SUMIF(Cronograma!$B$4:Cronograma!$B$51,1,Cronograma!$J$4:Cronograma!$J$51) | C8: =SUMIF(Cronograma!$B$4:Cronograma!$B$51,2,Cronograma!$J$4:Cronograma!$J$51) | D8: =SUMIF(Cronograma!$B$4:Cronograma!$B$51,3,Cronograma!$J$4:Cronograma!$J$51) | E8: =SUMIF(Cronograma!$B$4:Cronograma!$B$51,4,Cronograma!$J$4:Cronograma!$J$51) | F8: =B8+C8+D8+E8
A9: (-) Admin & Marketing | B9: =SUMIF(Cronograma!$B$4:Cronograma!$B$51,1,Cronograma!$F$4:Cronograma!$F$51)+SUMIF(Cronograma!$B$4:Cronograma!$B$51,1,Cronograma!$K$4:Cronograma!$K$51) | C9: =SUMIF(Cronograma!$B$4:Cronograma!$B$51,2,Cronograma!$F$4:Cronograma!$F$51)+SUMIF(Cronograma!$B$4:Cronograma!$B$51,2,Cronograma!$K$4:Cronograma!$K$51) | D9: =SUMIF(Cronograma!$B$4:Cronograma!$B$51,3,Cronograma!$F$4:Cronograma!$F$51)+SUMIF(Cronograma!$B$4:Cronograma!$B$51,3,Cronograma!$K$4:Cronograma!$K$51) | E9: =SUMIF(Cronograma!$B$4:Cronograma!$B$51,4,Cronograma!$F$4:Cronograma!$F$51)+SUMIF(Cronograma!$B$4:Cronograma!$B$51,4,Cronograma!$K$4:Cronograma!$K$51) | F9: =B9+C9+D9+E9
A10: (-) Contingência | B10: =SUMIF(Cronograma!$B$4:Cronograma!$B$51,1,Cronograma!$L$4:Cronograma!$L$51) | C10: =SUMIF(Cronograma!$B$4:Cronograma!$B$51,2,Cronograma!$L$4:Cronograma!$L$51) | D10: =SUMIF(Cronograma!$B$4:Cronograma!$B$51,3,Cronograma!$L$4:Cronograma!$L$51) | E10: =SUMIF(Cronograma!$B$4:Cronograma!$B$51,4,Cronograma!$L$4:Cronograma!$L$51) | F10: =B10+C10+D10+E10
A11: TOTAL CUSTOS | B11: =SUMIF(Cronograma!$B$4:Cronograma!$B$51,1,Cronograma!$M$4:Cronograma!$M$51) | C11: =SUMIF(Cronograma!$B$4:Cronograma!$B$51,2,Cronograma!$M$4:Cronograma!$M$51) | D11: =SUMIF(Cronograma!$B$4:Cronograma!$B$51,3,Cronograma!$M$4:Cronograma!$M$51) | E11: =SUMIF(Cronograma!$B$4:Cronograma!$B$51,4,Cronograma!$M$4:Cronograma!$M$51) | F11: =B11+C11+D11+E11
A12: Resultado Bruto | B12: =SUMIF(Cronograma!$B$4:Cronograma!$B$51,1,Cronograma!$N$4:Cronograma!$N$51) | C12: =SUMIF(Cronograma!$B$4:Cronograma!$B$51,2,Cronograma!$N$4:Cronograma!$N$51) | D12: =SUMIF(Cronograma!$B$4:Cronograma!$B$51,3,Cronograma!$N$4:Cronograma!$N$51) | E12: =SUMIF(Cronograma!$B$4:Cronograma!$B$51,4,Cronograma!$N$4:Cronograma!$N$51) | F12: =B12+C12+D12+E12
A13: (-) Pagto. Terrenista | B13: =SUMIF(Cronograma!$B$4:Cronograma!$B$51,1,Cronograma!$O$4:Cronograma!$O$51) | C13: =SUMIF(Cronograma!$B$4:Cronograma!$B$51,2,Cronograma!$O$4:Cronograma!$O$51) | D13: =SUMIF(Cronograma!$B$4:Cronograma!$B$51,3,Cronograma!$O$4:Cronograma!$O$51) | E13: =SUMIF(Cronograma!$B$4:Cronograma!$B$51,4,Cronograma!$O$4:Cronograma!$O$51) | F13: =B13+C13+D13+E13
A14: (-) Impostos | B14: =SUMIF(Cronograma!$B$4:Cronograma!$B$51,1,Cronograma!$Q$4:Cronograma!$Q$51) | C14: =SUMIF(Cronograma!$B$4:Cronograma!$B$51,2,Cronograma!$Q$4:Cronograma!$Q$51) | D14: =SUMIF(Cronograma!$B$4:Cronograma!$B$51,3,Cronograma!$Q$4:Cronograma!$Q$51) | E14: =SUMIF(Cronograma!$B$4:Cronograma!$B$51,4,Cronograma!$Q$4:Cronograma!$Q$51) | F14: =B14+C14+D14+E14
A15: (-) Custo Financeiro | B15: =SUMIF(Cronograma!$B$4:Cronograma!$B$51,1,Cronograma!$R$4:Cronograma!$R$51) | C15: =SUMIF(Cronograma!$B$4:Cronograma!$B$51,2,Cronograma!$R$4:Cronograma!$R$51) | D15: =SUMIF(Cronograma!$B$4:Cronograma!$B$51,3,Cronograma!$R$4:Cronograma!$R$51) | E15: =SUMIF(Cronograma!$B$4:Cronograma!$B$51,4,Cronograma!$R$4:Cronograma!$R$51) | F15: =B15+C15+D15+E15
A16: FLUXO LÍQUIDO EMPREENDEDOR | B16: =SUMIF(Cronograma!$B$4:Cronograma!$B$51,1,Cronograma!$S$4:Cronograma!$S$51) | C16: =SUMIF(Cronograma!$B$4:Cronograma!$B$51,2,Cronograma!$S$4:Cronograma!$S$51) | D16: =SUMIF(Cronograma!$B$4:Cronograma!$B$51,3,Cronograma!$S$4:Cronograma!$S$51) | E16: =SUMIF(Cronograma!$B$4:Cronograma!$B$51,4,Cronograma!$S$4:Cronograma!$S$51) | F16: =B16+C16+D16+E16
A17: SALDO ACUMULADO (final ano) | B17: =Cronograma!$T$15 | C17: =Cronograma!$T$27 | D17: =Cronograma!$T$39 | E17: =Cronograma!$T$51 | F17: =Cronograma!$T$51
A19: INDICADORES CHAVE (vínculos com Parâmetros)
A20: VGV Total | B20: =Parâmetros!$B$6
A21: Preço por lote | B21: =Parâmetros!$B$4
A22: Total de lotes | B22: =Parâmetros!$B$5
A23: % Empreendedor | B23: =Parâmetros!$B$18
A24: % Terrenista | B24: =Parâmetros!$B$19
A25: Capital próprio investido | B25: =Parâmetros!$B$21
A26: Infra total | B26: =Parâmetros!$B$24

Sheet Parâmetros
A1: PARÂMETROS — altere aqui e todo o fluxo de caixa recalcula
A2: 🟡 Amarelo = editável | 🔵 Azul = calculado automaticamente
A3: COMERCIAL
A4: Preço de venda por lote (R$) | B4: 80000 | C4: R$ | D4: Entrada — loteamento popular
A5: Total de lotes | B5: 330 | C5: un. | D5: Aprovado pelo projeto urbanístico
A6: VGV Total (R$) | B6: =B4*B5 | C6: R$ | D6: Calculado
A7: FINANCIAMENTO
A8: % lotes à vista / banco | B8: 0.7 | D8: 70% recebido na venda
A9: % lotes financiados empreendedor | B9: =1-B8 | D9: Calculado
A10: Prazo financiamento (meses) | B10: 60 | C10: meses | D10: Máximo 60 meses
A11: Parcela por lote (R$/mês) | B11: =B4*B9/B10 | C11: R$/lote/mês | D11: Calculado
A12: TAXAS E PERCENTUAIS
A13: Taxa de corretagem | B13: 0.06 | C13: % venda | D13: 6% sobre valor de venda
A14: Taxa administração (% VGV) | B14: 0.03 | C14: % VGV | D14: 3% do VGV total
A15: Taxa marketing (% VGV) | B15: 0.02 | C15: % VGV | D15: 2% do VGV total
A16: Taxa contingência | B16: 0.03 | C16: % custos | D16: 3% sobre custos diretos
A17: Taxa impostos — Lucro Presumido | B17: 0.065 | C17: % receita | D17: PIS+COFINS+IRPJ+CSLL
A18: % Empreendedor | B18: 0.65 | D18: Base: lucro antes dos impostos
A19: % Terrenista | B19: =1-B18 | D19: Calculado
A20: CAPITAL
A21: Capital próprio investido (R$) | B21: 1000000 | C21: R$ | D21: Aporte inicial — mês 0
A22: Taxa custo financeiro (a.m.) | B22: 0.015 | C22: a.m. | D22: 1,5% sobre saldo negativo acum.
A23: INFRAESTRUTURA
A24: Total infraestrutura (R$) | B24: 5430000 | C24: R$ | D24: Da aba Infraestrutura — pode vincular se quiser
A26: 💡 DICA: Para vincular o total da infra automaticamente, substitua o valor de B24 pela fórmula: =Viabilidade!Infraestrutura!E14 (após gerar a planilha principal)

Sheet Cronograma
A1: CRONOGRAMA MESTRE — motor de cálculo — todas as fórmulas ligadas a Parâmetros
A2: IDENTIFICAÇÃO | D2: ENTRADAS (EDITÁVEIS) | G2: RECEITAS | J2: CUSTOS | N2: RESULTADO BRUTO | Q2: RESULTADO LÍQUIDO EMPREENDEDOR
A3: MÊS | B3: ANO | C3: MÊS NOME | D3: LOTES VENDIDOS | E3: INFRA- ESTRUTURA | F3: MARKETING MENSAL | G3: RECEITA À VISTA | H3: PARCELAS RECEB. | I3: TOTAL RECEITA | J3: CORRETA- GEM | K3: ADMIN MENSAL | L3: CONTIN- GÊNCIA | M3: TOTAL CUSTOS | N3: RESULTADO BRUTO | O3: PAGTO. TERRENISTA | P3: RES.EMPREEN- DEDOR | Q3: IMPOSTOS | R3: CUSTO FINANC. | S3: FLUXO LÍQUIDO | T3: FLUXO ACUMULADO
A4: 1 | B4: =INT((A4-1)/12)+1 | C4: Janeiro | D4: 0 | E4: 50000 | F4: 0 | G4: =D4*Parâmetros!$B$4*Parâmetros!$B$8 | H4: 0 | I4: =G4+H4 | J4: =D4*Parâmetros!$B$4*Parâmetros!$B$13 | K4: =Parâmetros!$B$6*Parâmetros!$B$14/48 | L4: =(E4+F4+J4+K4)*Parâmetros!$B$16 | M4: =E4+F4+J4+K4+L4 | N4: =I4-M4 | O4: =MAX(0,N4)*Parâmetros!$B$19 | P4: =N4-O4 | Q4: =I4*Parâmetros!$B$17 | R4: =Parâmetros!$B$21*Parâmetros!$B$22 | S4: =P4-Q4-R4 | T4: =S4-Parâmetros!$B$21
A5: 2 | B5: =INT((A5-1)/12)+1 | C5: Fevereiro | D5: 0 | E5: 100000 | F5: 0 | G5: =D5*Parâmetros!$B$4*Parâmetros!$B$8 | H5: =SUMPRODUCT(($D$4:D4)*($A$4:A4>=(A5-Parâmetros!$B$10)))*Parâmetros!$B$11 | I5: =G5+H5 | J5: =D5*Parâmetros!$B$4*Parâmetros!$B$13 | K5: =Parâmetros!$B$6*Parâmetros!$B$14/48 | L5: =(E5+F5+J5+K5)*Parâmetros!$B$16 | M5: =E5+F5+J5+K5+L5 | N5: =I5-M5 | O5: =MAX(0,N5)*Parâmetros!$B$19 | P5: =N5-O5 | Q5: =I5*Parâmetros!$B$17 | R5: =MAX(0,-T4)*Parâmetros!$B$22 | S5: =P5-Q5-R5 | T5: =T4+S5
A6: 3 | B6: =INT((A6-1)/12)+1 | C6: Março | D6: 0 | E6: 100000 | F6: 0 | G6: =D6*Parâmetros!$B$4*Parâmetros!$B$8 | H6: =SUMPRODUCT(($D$4:D5)*($A$4:A5>=(A6-Parâmetros!$B$10)))*Parâmetros!$B$11 | I6: =G6+H6 | J6: =D6*Parâmetros!$B$4*Parâmetros!$B$13 | K6: =Parâmetros!$B$6*Parâmetros!$B$14/48 | L6: =(E6+F6+J6+K6)*Parâmetros!$B$16 | M6: =E6+F6+J6+K6+L6 | N6: =I6-M6 | O6: =MAX(0,N6)*Parâmetros!$B$19 | P6: =N6-O6 | Q6: =I6*Parâmetros!$B$17 | R6: =MAX(0,-T5)*Parâmetros!$B$22 | S6: =P6-Q6-R6 | T6: =T5+S6
A7: 4 | B7: =INT((A7-1)/12)+1 | C7: Abril | D7: 0 | E7: 200000 | F7: 0 | G7: =D7*Parâmetros!$B$4*Parâmetros!$B$8 | H7: =SUMPRODUCT(($D$4:D6)*($A$4:A6>=(A7-Parâmetros!$B$10)))*Parâmetros!$B$11 | I7: =G7+H7 | J7: =D7*Parâmetros!$B$4*Parâmetros!$B$13 | K7: =Parâmetros!$B$6*Parâmetros!$B$14/48 | L7: =(E7+F7+J7+K7)*Parâmetros!$B$16 | M7: =E7+F7+J7+K7+L7 | N7: =I7-M7 | O7: =MAX(0,N7)*Parâmetros!$B$19 | P7: =N7-O7 | Q7: =I7*Parâmetros!$B$17 | R7: =MAX(0,-T6)*Parâmetros!$B$22 | S7: =P7-Q7-R7 | T7: =T6+S7
A8: 5 | B8: =INT((A8-1)/12)+1 | C8: Maio | D8: 0 | E8: 300000 | F8: 50000 | G8: =D8*Parâmetros!$B$4*Parâmetros!$B$8 | H8: =SUMPRODUCT(($D$4:D7)*($A$4:A7>=(A8-Parâmetros!$B$10)))*Parâmetros!$B$11 | I8: =G8+H8 | J8: =D8*Parâmetros!$B$4*Parâmetros!$B$13 | K8: =Parâmetros!$B$6*Parâmetros!$B$14/48 | L8: =(E8+F8+J8+K8)*Parâmetros!$B$16 | M8: =E8+F8+J8+K8+L8 | N8: =I8-M8 | O8: =MAX(0,N8)*Parâmetros!$B$19 | P8: =N8-O8 | Q8: =I8*Parâmetros!$B$17 | R8: =MAX(0,-T7)*Parâmetros!$B$22 | S8: =P8-Q8-R8 | T8: =T7+S8
A9: 6 | B9: =INT((A9-1)/12)+1 | C9: Junho | D9: 0 | E9: 300000 | F9: 100000 | G9: =D9*Parâmetros!$B$4*Parâmetros!$B$8 | H9: =SUMPRODUCT(($D$4:D8)*($A$4:A8>=(A9-Parâmetros!$B$10)))*Parâmetros!$B$11 | I9: =G9+H9 | J9: =D9*Parâmetros!$B$4*Parâmetros!$B$13 | K9: =Parâmetros!$B$6*Parâmetros!$B$14/48 | L9: =(E9+F9+J9+K9)*Parâmetros!$B$16 | M9: =E9+F9+J9+K9+L9 | N9: =I9-M9 | O9: =MAX(0,N9)*Parâmetros!$B$19 | P9: =N9-O9 | Q9: =I9*Parâmetros!$B$17 | R9: =MAX(0,-T8)*Parâmetros!$B$22 | S9: =P9-Q9-R9 | T9: =T8+S9
A10: 7 | B10: =INT((A10-1)/12)+1 | C10: Julho | D10: 40 | E10: 400000 | F10: 100000 | G10: =D10*Parâmetros!$B$4*Parâmetros!$B$8 | H10: =SUMPRODUCT(($D$4:D9)*($A$4:A9>=(A10-Parâmetros!$B$10)))*Parâmetros!$B$11 | I10: =G10+H10 | J10: =D10*Parâmetros!$B$4*Parâmetros!$B$13 | K10: =Parâmetros!$B$6*Parâmetros!$B$14/48 | L10: =(E10+F10+J10+K10)*Parâmetros!$B$16 | M10: =E10+F10+J10+K10+L10 | N10: =I10-M10 | O10: =MAX(0,N10)*Parâmetros!$B$19 | P10: =N10-O10 | Q10: =I10*Parâmetros!$B$17 | R10: =MAX(0,-T9)*Parâmetros!$B$22 | S10: =P10-Q10-R10 | T10: =T9+S10
A11: 8 | B11: =INT((A11-1)/12)+1 | C11: Agosto | D11: 10 | E11: 400000 | F11: 50000 | G11: =D11*Parâmetros!$B$4*Parâmetros!$B$8 | H11: =SUMPRODUCT(($D$4:D10)*($A$4:A10>=(A11-Parâmetros!$B$10)))*Parâmetros!$B$11 | I11: =G11+H11 | J11: =D11*Parâmetros!$B$4*Parâmetros!$B$13 | K11: =Parâmetros!$B$6*Parâmetros!$B$14/48 | L11: =(E11+F11+J11+K11)*Parâmetros!$B$16 | M11: =E11+F11+J11+K11+L11 | N11: =I11-M11 | O11: =MAX(0,N11)*Parâmetros!$B$19 | P11: =N11-O11 | Q11: =I11*Parâmetros!$B$17 | R11: =MAX(0,-T10)*Parâmetros!$B$22 | S11: =P11-Q11-R11 | T11: =T10+S11
A12: 9 | B12: =INT((A12-1)/12)+1 | C12: Setembro | D12: 10 | E12: 400000 | F12: 30000 | G12: =D12*Parâmetros!$B$4*Parâmetros!$B$8 | H12: =SUMPRODUCT(($D$4:D11)*($A$4:A11>=(A12-Parâmetros!$B$10)))*Parâmetros!$B$11 | I12: =G12+H12 | J12: =D12*Parâmetros!$B$4*Parâmetros!$B$13 | K12: =Parâmetros!$B$6*Parâmetros!$B$14/48 | L12: =(E12+F12+J12+K12)*Parâmetros!$B$16 | M12: =E12+F12+J12+K12+L12 | N12: =I12-M12 | O12: =MAX(0,N12)*Parâmetros!$B$19 | P12: =N12-O12 | Q12: =I12*Parâmetros!$B$17 | R12: =MAX(0,-T11)*Parâmetros!$B$22 | S12: =P12-Q12-R12 | T12: =T11+S12
A13: 10 | B13: =INT((A13-1)/12)+1 | C13: Outubro | D13: 10 | E13: 400000 | F13: 20000 | G13: =D13*Parâmetros!$B$4*Parâmetros!$B$8 | H13: =SUMPRODUCT(($D$4:D12)*($A$4:A12>=(A13-Parâmetros!$B$10)))*Parâmetros!$B$11 | I13: =G13+H13 | J13: =D13*Parâmetros!$B$4*Parâmetros!$B$13 | K13: =Parâmetros!$B$6*Parâmetros!$B$14/48 | L13: =(E13+F13+J13+K13)*Parâmetros!$B$16 | M13: =E13+F13+J13+K13+L13 | N13: =I13-M13 | O13: =MAX(0,N13)*Parâmetros!$B$19 | P13: =N13-O13 | Q13: =I13*Parâmetros!$B$17 | R13: =MAX(0,-T12)*Parâmetros!$B$22 | S13: =P13-Q13-R13 | T13: =T12+S13
A14: 11 | B14: =INT((A14-1)/12)+1 | C14: Novembro | D14: 10 | E14: 400000 | F14: 20000 | G14: =D14*Parâmetros!$B$4*Parâmetros!$B$8 | H14: =SUMPRODUCT(($D$4:D13)*($A$4:A13>=(A14-Parâmetros!$B$10)))*Parâmetros!$B$11 | I14: =G14+H14 | J14: =D14*Parâmetros!$B$4*Parâmetros!$B$13 | K14: =Parâmetros!$B$6*Parâmetros!$B$14/48 | L14: =(E14+F14+J14+K14)*Parâmetros!$B$16 | M14: =E14+F14+J14+K14+L14 | N14: =I14-M14 | O14: =MAX(0,N14)*Parâmetros!$B$19 | P14: =N14-O14 | Q14: =I14*Parâmetros!$B$17 | R14: =MAX(0,-T13)*Parâmetros!$B$22 | S14: =P14-Q14-R14 | T14: =T13+S14
A15: 12 | B15: =INT((A15-1)/12)+1 | C15: Dezembro | D15: 10 | E15: 380000 | F15: 20000 | G15: =D15*Parâmetros!$B$4*Parâmetros!$B$8 | H15: =SUMPRODUCT(($D$4:D14)*($A$4:A14>=(A15-Parâmetros!$B$10)))*Parâmetros!$B$11 | I15: =G15+H15 | J15: =D15*Parâmetros!$B$4*Parâmetros!$B$13 | K15: =Parâmetros!$B$6*Parâmetros!$B$14/48 | L15: =(E15+F15+J15+K15)*Parâmetros!$B$16 | M15: =E15+F15+J15+K15+L15 | N15: =I15-M15 | O15: =MAX(0,N15)*Parâmetros!$B$19 | P15: =N15-O15 | Q15: =I15*Parâmetros!$B$17 | R15: =MAX(0,-T14)*Parâmetros!$B$22 | S15: =P15-Q15-R15 | T15: =T14+S15
A16: 13 | B16: =INT((A16-1)/12)+1 | C16: Janeiro | D16: 10 | E16: 350000 | F16: 5000 | G16: =D16*Parâmetros!$B$4*Parâmetros!$B$8 | H16: =SUMPRODUCT(($D$4:D15)*($A$4:A15>=(A16-Parâmetros!$B$10)))*Parâmetros!$B$11 | I16: =G16+H16 | J16: =D16*Parâmetros!$B$4*Parâmetros!$B$13 | K16: =Parâmetros!$B$6*Parâmetros!$B$14/48 | L16: =(E16+F16+J16+K16)*Parâmetros!$B$16 | M16: =E16+F16+J16+K16+L16 | N16: =I16-M16 | O16: =MAX(0,N16)*Parâmetros!$B$19 | P16: =N16-O16 | Q16: =I16*Parâmetros!$B$17 | R16: =MAX(0,-T15)*Parâmetros!$B$22 | S16: =P16-Q16-R16 | T16: =T15+S16
... A51: 48 | B51: =INT((A51-1)/12)+1 | C51: Dezembro | D51: 0 | E51: 8333 | F51: 3250 | G51: =D51*Parâmetros!$B$4*Parâmetros!$B$8 | H51: =SUMPRODUCT(($D$4:D50)*($A$4:A50>=(A51-Parâmetros!$B$10)))*Parâmetros!$B$11 | I51: =G51+H51 | J51: =D51*Parâmetros!$B$4*Parâmetros!$B$13 | K51: =Parâmetros!$B$6*Parâmetros!$B$14/48 | L51: =(E51+F51+J51+K51)*Parâmetros!$B$16 | M51: =E51+F51+J51+K51+L51 | N51: =I51-M51 | O51: =MAX(0,N51)*Parâmetros!$B$19 | P51: =N51-O51 | Q51: =I51*Parâmetros!$B$17 | R51: =MAX(0,-T50)*Parâmetros!$B$22 | S51: =P51-Q51-R51 | T51: =T50+S51
A52: TOTAL 48 MESES | D52: =SUM(D4:D51) | E52: =SUM(E4:E51) | F52: =SUM(F4:F51) | G52: =SUM(G4:G51) | H52: =SUM(H4:H51) | I52: =SUM(I4:I51) | J52: =SUM(J4:J51) | K52: =SUM(K4:K51) | ... S52: =SUM(S4:S51) | T52: =T51

Sheet Ano 1
A1: FLUXO DE CAIXA — ANO 1 — Janeiro a Dezembro — LOTEAMENTO PAPAGAIOS/MG
A2: =TEXT(SUMIF(Cronograma!$B$4:Cronograma!$B$51,1,Cronograma!$D$4:Cronograma!$D$51),"#,##0")&" lotes vendidos | Receita: "&TEXT(SUMIF(Cronograma!$B$4:Cronograma!$B$51,1,Cronograma!$I$4:Cronograma!$I$51),"R$ #,##0")&" | Fluxo Líq.: "&TEXT(SUMIF(Cronograma!$B$4:Cronograma!$B$51,1,Cronograma!$S$4:Cronograma!$S$51),"R$ #,##0")
A3: MÊS | B3: LOTES VEND. | C3: RECEITA À VISTA | D3: PARCELAS RECEB. | E3: TOTAL RECEITA | F3: (-) INFRA- ESTR. | G3: (-) CORRE- TAGEM | H3: (-) ADMIN & MKT | I3: (-) CONTIN- GÊNC. | J3: TOTAL CUSTOS | K3: RESULT. BRUTO | L3: (-) TERR- ENISTA | M3: (-) IMPOS- TOS | N3: (-) CUSTO FINANC. | O3: FLUXO LÍQUIDO | P3: FLUXO ACUMUL.
A4: =Cronograma!C4 | B4: =Cronograma!D4 | C4: =Cronograma!G4 | D4: =Cronograma!H4 | E4: =Cronograma!I4 | F4: =Cronograma!E4 | G4: =Cronograma!J4 | H4: =Cronograma!F4+Cronograma!K4 | I4: =Cronograma!L4 | J4: =Cronograma!M4 | K4: =Cronograma!N4 | L4: =Cronograma!O4 | M4: =Cronograma!Q4 | N4: =Cronograma!R4 | O4: =Cronograma!S4 | P4: =Cronograma!T4
A5: =Cronograma!C5 | B5: =Cronograma!D5 | C5: =Cronograma!G5 | D5: =Cronograma!H5 | E5: =Cronograma!I5 | F5: =Cronograma!E5 | G5: =Cronograma!J5 | H5: =Cronograma!F5+Cronograma!K5 | I5: =Cronograma!L5 | J5: =Cronograma!M5 | K5: =Cronograma!N5 | L5: =Cronograma!O5 | M5: =Cronograma!Q5 | N5: =Cronograma!R5 | O5: =Cronograma!S5 | P5: =Cronograma!T5
A6: =Cronograma!C6 | B6: =Cronograma!D6 | C6: =Cronograma!G6 | D6: =Cronograma!H6 | E6: =Cronograma!I6 | F6: =Cronograma!E6 | G6: =Cronograma!J6 | H6: =Cronograma!F6+Cronograma!K6 | I6: =Cronograma!L6 | J6: =Cronograma!M6 | K6: =Cronograma!N6 | L6: =Cronograma!O6 | M6: =Cronograma!Q6 | N6: =Cronograma!R6 | O6: =Cronograma!S6 | P6: =Cronograma!T6
A7: =Cronograma!C7 | B7: =Cronograma!D7 | C7: =Cronograma!G7 | D7: =Cronograma!H7 | E7: =Cronograma!I7 | F7: =Cronograma!E7 | G7: =Cronograma!J7 | H7: =Cronograma!F7+Cronograma!K7 | I7: =Cronograma!L7 | J7: =Cronograma!M7 | K7: =Cronograma!N7 | L7: =Cronograma!O7 | M7: =Cronograma!Q7 | N7: =Cronograma!R7 | O7: =Cronograma!S7 | P7: =Cronograma!T7
A8: =Cronograma!C8 | B8: =Cronograma!D8 | C8: =Cronograma!G8 | D8: =Cronograma!H8 | E8: =Cronograma!I8 | F8: =Cronograma!E8 | G8: =Cronograma!J8 | H8: =Cronograma!F8+Cronograma!K8 | I8: =Cronograma!L8 | J8: =Cronograma!M8 | K8: =Cronograma!N8 | L8: =Cronograma!O8 | M8: =Cronograma!Q8 | N8: =Cronograma!R8 | O8: =Cronograma!S8 | P8: =Cronograma!T8
A9: =Cronograma!C9 | B9: =Cronograma!D9 | C9: =Cronograma!G9 | D9: =Cronograma!H9 | E9: =Cronograma!I9 | F9: =Cronograma!E9 | G9: =Cronograma!J9 | H9: =Cronograma!F9+Cronograma!K9 | I9: =Cronograma!L9 | J9: =Cronograma!M9 | K9: =Cronograma!N9 | L9: =Cronograma!O9 | M9: =Cronograma!Q9 | N9: =Cronograma!R9 | O9: =Cronograma!S9 | P9: =Cronograma!T9
A10: =Cronograma!C10 | B10: =Cronograma!D10 | C10: =Cronograma!G10 | D10: =Cronograma!H10 | E10: =Cronograma!I10 | F10: =Cronograma!E10 | G10: =Cronograma!J10 | H10: =Cronograma!F10+Cronograma!K10 | I10: =Cronograma!L10 | J10: =Cronograma!M10 | K10: =Cronograma!N10 | L10: =Cronograma!O10 | M10: =Cronograma!Q10 | N10: =Cronograma!R10 | O10: =Cronograma!S10 | P10: =Cronograma!T10
A11: =Cronograma!C11 | B11: =Cronograma!D11 | C11: =Cronograma!G11 | D11: =Cronograma!H11 | E11: =Cronograma!I11 | F11: =Cronograma!E11 | G11: =Cronograma!J11 | H11: =Cronograma!F11+Cronograma!K11 | I11: =Cronograma!L11 | J11: =Cronograma!M11 | K11: =Cronograma!N11 | L11: =Cronograma!O11 | M11: =Cronograma!Q11 | N11: =Cronograma!R11 | O11: =Cronograma!S11 | P11: =Cronograma!T11
A12: =Cronograma!C12 | B12: =Cronograma!D12 | C12: =Cronograma!G12 | D12: =Cronograma!H12 | E12: =Cronograma!I12 | F12: =Cronograma!E12 | G12: =Cronograma!J12 | H12: =Cronograma!F12+Cronograma!K12 | I12: =Cronograma!L12 | J12: =Cronograma!M12 | K12: =Cronograma!N12 | L12: =Cronograma!O12 | M12: =Cronograma!Q12 | N12: =Cronograma!R12 | O12: =Cronograma!S12 | P12: =Cronograma!T12
A13: =Cronograma!C13 | B13: =Cronograma!D13 | C13: =Cronograma!G13 | D13: =Cronograma!H13 | E13: =Cronograma!I13 | F13: =Cronograma!E13 | G13: =Cronograma!J13 | H13: =Cronograma!F13+Cronograma!K13 | I13: =Cronograma!L13 | J13: =Cronograma!M13 | K13: =Cronograma!N13 | L13: =Cronograma!O13 | M13: =Cronograma!Q13 | N13: =Cronograma!R13 | O13: =Cronograma!S13 | P13: =Cronograma!T13
A14: =Cronograma!C14 | B14: =Cronograma!D14 | C14: =Cronograma!G14 | D14: =Cronograma!H14 | E14: =Cronograma!I14 | F14: =Cronograma!E14 | G14: =Cronograma!J14 | H14: =Cronograma!F14+Cronograma!K14 | I14: =Cronograma!L14 | J14: =Cronograma!M14 | K14: =Cronograma!N14 | L14: =Cronograma!O14 | M14: =Cronograma!Q14 | N14: =Cronograma!R14 | O14: =Cronograma!S14 | P14: =Cronograma!T14
A15: =Cronograma!C15 | B15: =Cronograma!D15 | C15: =Cronograma!G15 | D15: =Cronograma!H15 | E15: =Cronograma!I15 | F15: =Cronograma!E15 | G15: =Cronograma!J15 | H15: =Cronograma!F15+Cronograma!K15 | I15: =Cronograma!L15 | J15: =Cronograma!M15 | K15: =Cronograma!N15 | L15: =Cronograma!O15 | M15: =Cronograma!Q15 | N15: =Cronograma!R15 | O15: =Cronograma!S15 | P15: =Cronograma!T15
A16: TOTAL ANO 1 | B16: =SUM(B4:B15) | C16: =SUM(C4:C15) | D16: =SUM(D4:D15) | E16: =SUM(E4:E15) | F16: =SUM(F4:F15) | G16: =SUM(G4:G15) | H16: =SUM(H4:H15) | I16: =SUM(I4:I15) | ... O16: =SUM(O4:O15) | P16: =Cronograma!T15
A18: 📌 Todos os valores são fórmulas vinculadas à aba Cronograma, que por sua vez vincula com Parâmetros. Para alterar qualquer premissa, edite apenas a aba Parâmetros.

Sheet Ano 2
A1: FLUXO DE CAIXA — ANO 2 — Janeiro a Dezembro — LOTEAMENTO PAPAGAIOS/MG
A2: =TEXT(SUMIF(Cronograma!$B$4:Cronograma!$B$51,2,Cronograma!$D$4:Cronograma!$D$51),"#,##0")&" lotes vendidos | Receita: "&TEXT(SUMIF(Cronograma!$B$4:Cronograma!$B$51,2,Cronograma!$I$4:Cronograma!$I$51),"R$ #,##0")&" | Fluxo Líq.: "&TEXT(SUMIF(Cronograma!$B$4:Cronograma!$B$51,2,Cronograma!$S$4:Cronograma!$S$51),"R$ #,##0")
A3: MÊS | B3: LOTES VEND. | C3: RECEITA À VISTA | D3: PARCELAS RECEB. | E3: TOTAL RECEITA | F3: (-) INFRA- ESTR. | G3: (-) CORRE- TAGEM | H3: (-) ADMIN & MKT | I3: (-) CONTIN- GÊNC. | J3: TOTAL CUSTOS | K3: RESULT. BRUTO | L3: (-) TERR- ENISTA | M3: (-) IMPOS- TOS | N3: (-) CUSTO FINANC. | O3: FLUXO LÍQUIDO | P3: FLUXO ACUMUL.
A4: =Cronograma!C16 | B4: =Cronograma!D16 | C4: =Cronograma!G16 | D4: =Cronograma!H16 | E4: =Cronograma!I16 | F4: =Cronograma!E16 | G4: =Cronograma!J16 | H4: =Cronograma!F16+Cronograma!K16 | I4: =Cronograma!L16 | J4: =Cronograma!M16 | K4: =Cronograma!N16 | L4: =Cronograma!O16 | M4: =Cronograma!Q16 | N4: =Cronograma!R16 | O4: =Cronograma!S16 | P4: =Cronograma!T16
A5: =Cronograma!C17 | B5: =Cronograma!D17 | C5: =Cronograma!G17 | D5: =Cronograma!H17 | E5: =Cronograma!I17 | F5: =Cronograma!E17 | G5: =Cronograma!J17 | H5: =Cronograma!F17+Cronograma!K17 | I5: =Cronograma!L17 | J5: =Cronograma!M17 | K5: =Cronograma!N17 | L5: =Cronograma!O17 | M5: =Cronograma!Q17 | N5: =Cronograma!R17 | O5: =Cronograma!S17 | P5: =Cronograma!T17
A6: =Cronograma!C18 | B6: =Cronograma!D18 | C6: =Cronograma!G18 | D6: =Cronograma!H18 | E6: =Cronograma!I18 | F6: =Cronograma!E18 | G6: =Cronograma!J18 | H6: =Cronograma!F18+Cronograma!K18 | I6: =Cronograma!L18 | J6: =Cronograma!M18 | K6: =Cronograma!N18 | L6: =Cronograma!O18 | M6: =Cronograma!Q18 | N6: =Cronograma!R18 | O6: =Cronograma!S18 | P6: =Cronograma!T18
A7: =Cronograma!C19 | B7: =Cronograma!D19 | C7: =Cronograma!G19 | D7: =Cronograma!H19 | E7: =Cronograma!I19 | F7: =Cronograma!E19 | G7: =Cronograma!J19 | H7: =Cronograma!F19+Cronograma!K19 | I7: =Cronograma!L19 | J7: =Cronograma!M19 | K7: =Cronograma!N19 | L7: =Cronograma!O19 | M7: =Cronograma!Q19 | N7: =Cronograma!R19 | O7: =Cronograma!S19 | P7: =Cronograma!T19
A8: =Cronograma!C20 | B8: =Cronograma!D20 | C8: =Cronograma!G20 | D8: =Cronograma!H20 | E8: =Cronograma!I20 | F8: =Cronograma!E20 | G8: =Cronograma!J20 | H8: =Cronograma!F20+Cronograma!K20 | I8: =Cronograma!L20 | J8: =Cronograma!M20 | K8: =Cronograma!N20 | L8: =Cronograma!O20 | M8: =Cronograma!Q20 | N8: =Cronograma!R20 | O8: =Cronograma!S20 | P8: =Cronograma!T20
A9: =Cronograma!C21 | B9: =Cronograma!D21 | C9: =Cronograma!G21 | D9: =Cronograma!H21 | E9: =Cronograma!I21 | F9: =Cronograma!E21 | G9: =Cronograma!J21 | H9: =Cronograma!F21+Cronograma!K21 | I9: =Cronograma!L21 | J9: =Cronograma!M21 | K9: =Cronograma!N21 | L9: =Cronograma!O21 | M9: =Cronograma!Q21 | N9: =Cronograma!R21 | O9: =Cronograma!S21 | P9: =Cronograma!T21
A10: =Cronograma!C22 | B10: =Cronograma!D22 | C10: =Cronograma!G22 | D10: =Cronograma!H22 | E10: =Cronograma!I22 | F10: =Cronograma!E22 | G10: =Cronograma!J22 | H10: =Cronograma!F22+Cronograma!K22 | I10: =Cronograma!L22 | J10: =Cronograma!M22 | K10: =Cronograma!N22 | L10: =Cronograma!O22 | M10: =Cronograma!Q22 | N10: =Cronograma!R22 | O10: =Cronograma!S22 | P10: =Cronograma!T22
A11: =Cronograma!C23 | B11: =Cronograma!D23 | C11: =Cronograma!G23 | D11: =Cronograma!H23 | E11: =Cronograma!I23 | F11: =Cronograma!E23 | G11: =Cronograma!J23 | H11: =Cronograma!F23+Cronograma!K23 | I11: =Cronograma!L23 | J11: =Cronograma!M23 | K11: =Cronograma!N23 | L11: =Cronograma!O23 | M11: =Cronograma!Q23 | N11: =Cronograma!R23 | O11: =Cronograma!S23 | P11: =Cronograma!T23
A12: =Cronograma!C24 | B12: =Cronograma!D24 | C12: =Cronograma!G24 | D12: =Cronograma!H24 | E12: =Cronograma!I24 | F12: =Cronograma!E24 | G12: =Cronograma!J24 | H12: =Cronograma!F24+Cronograma!K24 | I12: =Cronograma!L24 | J12: =Cronograma!M24 | K12: =Cronograma!N24 | L12: =Cronograma!O24 | M12: =Cronograma!Q24 | N12: =Cronograma!R24 | O12: =Cronograma!S24 | P12: =Cronograma!T24
A13: =Cronograma!C25 | B13: =Cronograma!D25 | C13: =Cronograma!G25 | D13: =Cronograma!H25 | E13: =Cronograma!I25 | F13: =Cronograma!E25 | G13: =Cronograma!J25 | H13: =Cronograma!F25+Cronograma!K25 | I13: =Cronograma!L25 | J13: =Cronograma!M25 | K13: =Cronograma!N25 | L13: =Cronograma!O25 | M13: =Cronograma!Q25 | N13: =Cronograma!R25 | O13: =Cronograma!S25 | P13: =Cronograma!T25
A14: =Cronograma!C26 | B14: =Cronograma!D26 | C14: =Cronograma!G26 | D14: =Cronograma!H26 | E14: =Cronograma!I26 | F14: =Cronograma!E26 | G14: =Cronograma!J26 | H14: =Cronograma!F26+Cronograma!K26 | I14: =Cronograma!L26 | J14: =Cronograma!M26 | K14: =Cronograma!N26 | L14: =Cronograma!O26 | M14: =Cronograma!Q26 | N14: =Cronograma!R26 | O14: =Cronograma!S26 | P14: =Cronograma!T26
A15: =Cronograma!C27 | B15: =Cronograma!D27 | C15: =Cronograma!G27 | D15: =Cronograma!H27 | E15: =Cronograma!I27 | F15: =Cronograma!E27 | G15: =Cronograma!J27 | H15: =Cronograma!F27+Cronograma!K27 | I15: =Cronograma!L27 | J15: =Cronograma!M27 | K15: =Cronograma!N27 | L15: =Cronograma!O27 | M15: =Cronograma!Q27 | N15: =Cronograma!R27 | O15: =Cronograma!S27 | P15: =Cronograma!T27
A16: TOTAL ANO 2 | B16: =SUM(B4:B15) | C16: =SUM(C4:C15) | D16: =SUM(D4:D15) | E16: =SUM(E4:E15) | F16: =SUM(F4:F15) | G16: =SUM(G4:G15) | H16: =SUM(H4:H15) | I16: =SUM(I4:I15) | ... O16: =SUM(O4:O15) | P16: =Cronograma!T27
A18: 📌 Todos os valores são fórmulas vinculadas à aba Cronograma, que por sua vez vincula com Parâmetros. Para alterar qualquer premissa, edite apenas a aba Parâmetros.

Sheet Ano 3
A1: FLUXO DE CAIXA — ANO 3 — Janeiro a Dezembro — LOTEAMENTO PAPAGAIOS/MG
A2: =TEXT(SUMIF(Cronograma!$B$4:Cronograma!$B$51,3,Cronograma!$D$4:Cronograma!$D$51),"#,##0")&" lotes vendidos | Receita: "&TEXT(SUMIF(Cronograma!$B$4:Cronograma!$B$51,3,Cronograma!$I$4:Cronograma!$I$51),"R$ #,##0")&" | Fluxo Líq.: "&TEXT(SUMIF(Cronograma!$B$4:Cronograma!$B$51,3,Cronograma!$S$4:Cronograma!$S$51),"R$ #,##0")
A3: MÊS | B3: LOTES VEND. | C3: RECEITA À VISTA | D3: PARCELAS RECEB. | E3: TOTAL RECEITA | F3: (-) INFRA- ESTR. | G3: (-) CORRE- TAGEM | H3: (-) ADMIN & MKT | I3: (-) CONTIN- GÊNC. | J3: TOTAL CUSTOS | K3: RESULT. BRUTO | L3: (-) TERR- ENISTA | M3: (-) IMPOS- TOS | N3: (-) CUSTO FINANC. | O3: FLUXO LÍQUIDO | P3: FLUXO ACUMUL.
A4: =Cronograma!C28 | B4: =Cronograma!D28 | C4: =Cronograma!G28 | D4: =Cronograma!H28 | E4: =Cronograma!I28 | F4: =Cronograma!E28 | G4: =Cronograma!J28 | H4: =Cronograma!F28+Cronograma!K28 | I4: =Cronograma!L28 | J4: =Cronograma!M28 | K4: =Cronograma!N28 | L4: =Cronograma!O28 | M4: =Cronograma!Q28 | N4: =Cronograma!R28 | O4: =Cronograma!S28 | P4: =Cronograma!T28
A5: =Cronograma!C29 | B5: =Cronograma!D29 | C5: =Cronograma!G29 | D5: =Cronograma!H29 | E5: =Cronograma!I29 | F5: =Cronograma!E29 | G5: =Cronograma!J29 | H5: =Cronograma!F29+Cronograma!K29 | I5: =Cronograma!L29 | J5: =Cronograma!M29 | K5: =Cronograma!N29 | L5: =Cronograma!O29 | M5: =Cronograma!Q29 | N5: =Cronograma!R29 | O5: =Cronograma!S29 | P5: =Cronograma!T29
A6: =Cronograma!C30 | B6: =Cronograma!D30 | C6: =Cronograma!G30 | D6: =Cronograma!H30 | E6: =Cronograma!I30 | F6: =Cronograma!E30 | G6: =Cronograma!J30 | H6: =Cronograma!F30+Cronograma!K30 | I6: =Cronograma!L30 | J6: =Cronograma!M30 | K6: =Cronograma!N30 | L6: =Cronograma!O30 | M6: =Cronograma!Q30 | N6: =Cronograma!R30 | O6: =Cronograma!S30 | P6: =Cronograma!T30
A7: =Cronograma!C31 | B7: =Cronograma!D31 | C7: =Cronograma!G31 | D7: =Cronograma!H31 | E7: =Cronograma!I31 | F7: =Cronograma!E31 | G7: =Cronograma!J31 | H7: =Cronograma!F31+Cronograma!K31 | I7: =Cronograma!L31 | J7: =Cronograma!M31 | K7: =Cronograma!N31 | L7: =Cronograma!O31 | M7: =Cronograma!Q31 | N7: =Cronograma!R31 | O7: =Cronograma!S31 | P7: =Cronograma!T31
A8: =Cronograma!C32 | B8: =Cronograma!D32 | C8: =Cronograma!G32 | D8: =Cronograma!H32 | E8: =Cronograma!I32 | F8: =Cronograma!E32 | G8: =Cronograma!J32 | H8: =Cronograma!F32+Cronograma!K32 | I8: =Cronograma!L32 | J8: =Cronograma!M32 | K8: =Cronograma!N32 | L8: =Cronograma!O32 | M8: =Cronograma!Q32 | N8: =Cronograma!R32 | O8: =Cronograma!S32 | P8: =Cronograma!T32
A9: =Cronograma!C33 | B9: =Cronograma!D33 | C9: =Cronograma!G33 | D9: =Cronograma!H33 | E9: =Cronograma!I33 | F9: =Cronograma!E33 | G9: =Cronograma!J33 | H9: =Cronograma!F33+Cronograma!K33 | I9: =Cronograma!L33 | J9: =Cronograma!M33 | K9: =Cronograma!N33 | L9: =Cronograma!O33 | M9: =Cronograma!Q33 | N9: =Cronograma!R33 | O9: =Cronograma!S33 | P9: =Cronograma!T33
A10: =Cronograma!C34 | B10: =Cronograma!D34 | C10: =Cronograma!G34 | D10: =Cronograma!H34 | E10: =Cronograma!I34 | F10: =Cronograma!E34 | G10: =Cronograma!J34 | H10: =Cronograma!F34+Cronograma!K34 | I10: =Cronograma!L34 | J10: =Cronograma!M34 | K10: =Cronograma!N34 | L10: =Cronograma!O34 | M10: =Cronograma!Q34 | N10: =Cronograma!R34 | O10: =Cronograma!S34 | P10: =Cronograma!T34
A11: =Cronograma!C35 | B11: =Cronograma!D35 | C11: =Cronograma!G35 | D11: =Cronograma!H35 | E11: =Cronograma!I35 | F11: =Cronograma!E35 | G11: =Cronograma!J35 | H11: =Cronograma!F35+Cronograma!K35 | I11: =Cronograma!L35 | J11: =Cronograma!M35 | K11: =Cronograma!N35 | L11: =Cronograma!O35 | M11: =Cronograma!Q35 | N11: =Cronograma!R35 | O11: =Cronograma!S35 | P11: =Cronograma!T35
A12: =Cronograma!C36 | B12: =Cronograma!D36 | C12: =Cronograma!G36 | D12: =Cronograma!H36 | E12: =Cronograma!I36 | F12: =Cronograma!E36 | G12: =Cronograma!J36 | H12: =Cronograma!F36+Cronograma!K36 | I12: =Cronograma!L36 | J12: =Cronograma!M36 | K12: =Cronograma!N36 | L12: =Cronograma!O36 | M12: =Cronograma!Q36 | N12: =Cronograma!R36 | O12: =Cronograma!S36 | P12: =Cronograma!T36
A13: =Cronograma!C37 | B13: =Cronograma!D37 | C13: =Cronograma!G37 | D13: =Cronograma!H37 | E13: =Cronograma!I37 | F13: =Cronograma!E37 | G13: =Cronograma!J37 | H13: =Cronograma!F37+Cronograma!K37 | I13: =Cronograma!L37 | J13: =Cronograma!M37 | K13: =Cronograma!N37 | L13: =Cronograma!O37 | M13: =Cronograma!Q37 | N13: =Cronograma!R37 | O13: =Cronograma!S37 | P13: =Cronograma!T37
A14: =Cronograma!C38 | B14: =Cronograma!D38 | C14: =Cronograma!G38 | D14: =Cronograma!H38 | E14: =Cronograma!I38 | F14: =Cronograma!E38 | G14: =Cronograma!J38 | H14: =Cronograma!F38+Cronograma!K38 | I14: =Cronograma!L38 | J14: =Cronograma!M38 | K14: =Cronograma!N38 | L14: =Cronograma!O38 | M14: =Cronograma!Q38 | N14: =Cronograma!R38 | O14: =Cronograma!S38 | P14: =Cronograma!T38
A15: =Cronograma!C39 | B15: =Cronograma!D39 | C15: =Cronograma!G39 | D15: =Cronograma!H39 | E15: =Cronograma!I39 | F15: =Cronograma!E39 | G15: =Cronograma!J39 | H15: =Cronograma!F39+Cronograma!K39 | I15: =Cronograma!L39 | J15: =Cronograma!M39 | K15: =Cronograma!N39 | L15: =Cronograma!O39 | M15: =Cronograma!Q39 | N15: =Cronograma!R39 | O15: =Cronograma!S39 | P15: =Cronograma!T39
A16: TOTAL ANO 3 | B16: =SUM(B4:B15) | C16: =SUM(C4:C15) | D16: =SUM(D4:D15) | E16: =SUM(E4:E15) | F16: =SUM(F4:F15) | G16: =SUM(G4:G15) | H16: =SUM(H4:H15) | I16: =SUM(I4:I15) | ... O16: =SUM(O4:O15) | P16: =Cronograma!T39
A18: 📌 Todos os valores são fórmulas vinculadas à aba Cronograma, que por sua vez vincula com Parâmetros. Para alterar qualquer premissa, edite apenas a aba Parâmetros.

Sheet Ano 4
A1: FLUXO DE CAIXA — ANO 4 — Janeiro a Dezembro — LOTEAMENTO PAPAGAIOS/MG
A2: =TEXT(SUMIF(Cronograma!$B$4:Cronograma!$B$51,4,Cronograma!$D$4:Cronograma!$D$51),"#,##0")&" lotes vendidos | Receita: "&TEXT(SUMIF(Cronograma!$B$4:Cronograma!$B$51,4,Cronograma!$I$4:Cronograma!$I$51),"R$ #,##0")&" | Fluxo Líq.: "&TEXT(SUMIF(Cronograma!$B$4:Cronograma!$B$51,4,Cronograma!$S$4:Cronograma!$S$51),"R$ #,##0")
A3: MÊS | B3: LOTES VEND. | C3: RECEITA À VISTA | D3: PARCELAS RECEB. | E3: TOTAL RECEITA | F3: (-) INFRA- ESTR. | G3: (-) CORRE- TAGEM | H3: (-) ADMIN & MKT | I3: (-) CONTIN- GÊNC. | J3: TOTAL CUSTOS | K3: RESULT. BRUTO | L3: (-) TERR- ENISTA | M3: (-) IMPOS- TOS | N3: (-) CUSTO FINANC. | O3: FLUXO LÍQUIDO | P3: FLUXO ACUMUL.
A4: =Cronograma!C40 | B4: =Cronograma!D40 | C4: =Cronograma!G40 | D4: =Cronograma!H40 | E4: =Cronograma!I40 | F4: =Cronograma!E40 | G4: =Cronograma!J40 | H4: =Cronograma!F40+Cronograma!K40 | I4: =Cronograma!L40 | J4: =Cronograma!M40 | K4: =Cronograma!N40 | L4: =Cronograma!O40 | M4: =Cronograma!Q40 | N4: =Cronograma!R40 | O4: =Cronograma!S40 | P4: =Cronograma!T40
A5: =Cronograma!C41 | B5: =Cronograma!D41 | C5: =Cronograma!G41 | D5: =Cronograma!H41 | E5: =Cronograma!I41 | F5: =Cronograma!E41 | G5: =Cronograma!J41 | H5: =Cronograma!F41+Cronograma!K41 | I5: =Cronograma!L41 | J5: =Cronograma!M41 | K5: =Cronograma!N41 | L5: =Cronograma!O41 | M5: =Cronograma!Q41 | N5: =Cronograma!R41 | O5: =Cronograma!S41 | P5: =Cronograma!T41
A6: =Cronograma!C42 | B6: =Cronograma!D42 | C6: =Cronograma!G42 | D6: =Cronograma!H42 | E6: =Cronograma!I42 | F6: =Cronograma!E42 | G6: =Cronograma!J42 | H6: =Cronograma!F42+Cronograma!K42 | I6: =Cronograma!L42 | J6: =Cronograma!M42 | K6: =Cronograma!N42 | L6: =Cronograma!O42 | M6: =Cronograma!Q42 | N6: =Cronograma!R42 | O6: =Cronograma!S42 | P6: =Cronograma!T42
A7: =Cronograma!C43 | B7: =Cronograma!D43 | C7: =Cronograma!G43 | D7: =Cronograma!H43 | E7: =Cronograma!I43 | F7: =Cronograma!E43 | G7: =Cronograma!J43 | H7: =Cronograma!F43+Cronograma!K43 | I7: =Cronograma!L43 | J7: =Cronograma!M43 | K7: =Cronograma!N43 | L7: =Cronograma!O43 | M7: =Cronograma!Q43 | N7: =Cronograma!R43 | O7: =Cronograma!S43 | P7: =Cronograma!T43
A8: =Cronograma!C44 | B8: =Cronograma!D44 | C8: =Cronograma!G44 | D8: =Cronograma!H44 | E8: =Cronograma!I44 | F8: =Cronograma!E44 | G8: =Cronograma!J44 | H8: =Cronograma!F44+Cronograma!K44 | I8: =Cronograma!L44 | J8: =Cronograma!M44 | K8: =Cronograma!N44 | L8: =Cronograma!O44 | M8: =Cronograma!Q44 | N8: =Cronograma!R44 | O8: =Cronograma!S44 | P8: =Cronograma!T44
A9: =Cronograma!C45 | B9: =Cronograma!D45 | C9: =Cronograma!G45 | D9: =Cronograma!H45 | E9: =Cronograma!I45 | F9: =Cronograma!E45 | G9: =Cronograma!J45 | H9: =Cronograma!F45+Cronograma!K45 | I9: =Cronograma!L45 | J9: =Cronograma!M45 | K9: =Cronograma!N45 | L9: =Cronograma!O45 | M9: =Cronograma!Q45 | N9: =Cronograma!R45 | O9: =Cronograma!S45 | P9: =Cronograma!T45
A10: =Cronograma!C46 | B10: =Cronograma!D46 | C10: =Cronograma!G46 | D10: =Cronograma!H46 | E10: =Cronograma!I46 | F10: =Cronograma!E46 | G10: =Cronograma!J46 | H10: =Cronograma!F46+Cronograma!K46 | I10: =Cronograma!L46 | J10: =Cronograma!M46 | K10: =Cronograma!N46 | L10: =Cronograma!O46 | M10: =Cronograma!Q46 | N10: =Cronograma!R46 | O10: =Cronograma!S46 | P10: =Cronograma!T46
A11: =Cronograma!C47 | B11: =Cronograma!D47 | C11: =Cronograma!G47 | D11: =Cronograma!H47 | E11: =Cronograma!I47 | F11: =Cronograma!E47 | G11: =Cronograma!J47 | H11: =Cronograma!F47+Cronograma!K47 | I11: =Cronograma!L47 | J11: =Cronograma!M47 | K11: =Cronograma!N47 | L11: =Cronograma!O47 | M11: =Cronograma!Q47 | N11: =Cronograma!R47 | O11: =Cronograma!S47 | P11: =Cronograma!T47
A12: =Cronograma!C48 | B12: =Cronograma!D48 | C12: =Cronograma!G48 | D12: =Cronograma!H48 | E12: =Cronograma!I48 | F12: =Cronograma!E48 | G12: =Cronograma!J48 | H12: =Cronograma!F48+Cronograma!K48 | I12: =Cronograma!L48 | J12: =Cronograma!M48 | K12: =Cronograma!N48 | L12: =Cronograma!O48 | M12: =Cronograma!Q48 | N12: =Cronograma!R48 | O12: =Cronograma!S48 | P12: =Cronograma!T48
A13: =Cronograma!C49 | B13: =Cronograma!D49 | C13: =Cronograma!G49 | D13: =Cronograma!H49 | E13: =Cronograma!I49 | F13: =Cronograma!E49 | G13: =Cronograma!J49 | H13: =Cronograma!F49+Cronograma!K49 | I13: =Cronograma!L49 | J13: =Cronograma!M49 | K13: =Cronograma!N49 | L13: =Cronograma!O49 | M13: =Cronograma!Q49 | N13: =Cronograma!R49 | O13: =Cronograma!S49 | P13: =Cronograma!T49
A14: =Cronograma!C50 | B14: =Cronograma!D50 | C14: =Cronograma!G50 | D14: =Cronograma!H50 | E14: =Cronograma!I50 | F14: =Cronograma!E50 | G14: =Cronograma!J50 | H14: =Cronograma!F50+Cronograma!K50 | I14: =Cronograma!L50 | J14: =Cronograma!M50 | K14: =Cronograma!N50 | L14: =Cronograma!O50 | M14: =Cronograma!Q50 | N14: =Cronograma!R50 | O14: =Cronograma!S50 | P14: =Cronograma!T50
A15: =Cronograma!C51 | B15: =Cronograma!D51 | C15: =Cronograma!G51 | D15: =Cronograma!H51 | E15: =Cronograma!I51 | F15: =Cronograma!E51 | G15: =Cronograma!J51 | H15: =Cronograma!F51+Cronograma!K51 | I15: =Cronograma!L51 | J15: =Cronograma!M51 | K15: =Cronograma!N51 | L15: =Cronograma!O51 | M15: =Cronograma!Q51 | N15: =Cronograma!R51 | O15: =Cronograma!S51 | P15: =Cronograma!T51
A16: TOTAL ANO 4 | B16: =SUM(B4:B15) | C16: =SUM(C4:C15) | D16: =SUM(D4:D15) | E16: =SUM(E4:E15) | F16: =SUM(F4:F15) | G16: =SUM(G4:G15) | H16: =SUM(H4:H15) | I16: =SUM(I4:I15) | ... O16: =SUM(O4:O15) | P16: =Cronograma!T51
A18: 📌 Todos os valores são fórmulas vinculadas à aba Cronograma, que por sua vez vincula com Parâmetros. Para alterar qualquer premissa, edite apenas a aba Parâmetros.
