Workbook

Sheet Resumo Anual
A1: RESUMO ANUAL — FLUXO DE CAIXA — LOTEAMENTO PAPAGAIOS/MG
A2: INDICADOR | B2: ANO 1 | C2: ANO 2 | D2: ANO 3 | E2: ANO 4 | F2: TOTAL 4 ANOS
A3: Lotes vendidos | B3: =SUMIF(Cronograma!$B$4:'Cronograma'!$B$51,1,Cronograma!$D$4:'Cronograma'!$D$51) -> 90 | C3: =SUMIF(Cronograma!$B$4:'Cronograma'!$B$51,2,Cronograma!$D$4:'Cronograma'!$D$51) -> 120 | D3: =SUMIF(Cronograma!$B$4:'Cronograma'!$B$51,3,Cronograma!$D$4:'Cronograma'!$D$51) -> 120 | E3: =SUMIF(Cronograma!$B$4:'Cronograma'!$B$51,4,Cronograma!$D$4:'Cronograma'!$D$51) -> 0 | F3: =B3+C3+D3+E3 -> 330
A4: Receita à vista | B4: =SUMIF(Cronograma!$B$4:'Cronograma'!$B$51,1,Cronograma!$G$4:'Cronograma'!$G$51) -> 4725000 | C4: =SUMIF(Cronograma!$B$4:'Cronograma'!$B$51,2,Cronograma!$G$4:'Cronograma'!$G$51) -> 6300000 | D4: =SUMIF(Cronograma!$B$4:'Cronograma'!$B$51,3,Cronograma!$G$4:'Cronograma'!$G$51) -> 6300000 | E4: =SUMIF(Cronograma!$B$4:'Cronograma'!$B$51,4,Cronograma!$G$4:'Cronograma'!$G$51) -> 0 | F4: =B4+C4+D4+E4 -> 17325000
A5: Parcelas recebidas | B5: =SUMIF(Cronograma!$B$4:'Cronograma'!$B$51,1,Cronograma!$H$4:'Cronograma'!$H$51) -> 56250 | C5: =SUMIF(Cronograma!$B$4:'Cronograma'!$B$51,2,Cronograma!$H$4:'Cronograma'!$H$51) -> 326250 | D5: =SUMIF(Cronograma!$B$4:'Cronograma'!$B$51,3,Cronograma!$H$4:'Cronograma'!$H$51) -> 596250 | E5: =SUMIF(Cronograma!$B$4:'Cronograma'!$B$51,4,Cronograma!$H$4:'Cronograma'!$H$51) -> 742500 | F5: =B5+C5+D5+E5 -> 1721250
A6: TOTAL RECEITA | B6: =SUMIF(Cronograma!$B$4:'Cronograma'!$B$51,1,Cronograma!$I$4:'Cronograma'!$I$51) -> 4781250 | C6: =SUMIF(Cronograma!$B$4:'Cronograma'!$B$51,2,Cronograma!$I$4:'Cronograma'!$I$51) -> 6626250 | D6: =SUMIF(Cronograma!$B$4:'Cronograma'!$B$51,3,Cronograma!$I$4:'Cronograma'!$I$51) -> 6896250 | E6: =SUMIF(Cronograma!$B$4:'Cronograma'!$B$51,4,Cronograma!$I$4:'Cronograma'!$I$51) -> 742500 | F6: =B6+C6+D6+E6 -> 19046250
A7: (-) Infraestrutura | B7: =SUMIF(Cronograma!$B$4:'Cronograma'!$B$51,1,Cronograma!$E$4:'Cronograma'!$E$51) -> 3430000 | C7: =SUMIF(Cronograma!$B$4:'Cronograma'!$B$51,2,Cronograma!$E$4:'Cronograma'!$E$51) -> 1800000 | D7: =SUMIF(Cronograma!$B$4:'Cronograma'!$B$51,3,Cronograma!$E$4:'Cronograma'!$E$51) -> 99996 | E7: =SUMIF(Cronograma!$B$4:'Cronograma'!$B$51,4,Cronograma!$E$4:'Cronograma'!$E$51) -> 99996 | F7: =B7+C7+D7+E7 -> 5429992
A8: (-) Corretagem | B8: =SUMIF(Cronograma!$B$4:'Cronograma'!$B$51,1,Cronograma!$J$4:'Cronograma'!$J$51) -> 405000 | C8: =SUMIF(Cronograma!$B$4:'Cronograma'!$B$51,2,Cronograma!$J$4:'Cronograma'!$J$51) -> 540000 | D8: =SUMIF(Cronograma!$B$4:'Cronograma'!$B$51,3,Cronograma!$J$4:'Cronograma'!$J$51) -> 540000 | E8: =SUMIF(Cronograma!$B$4:'Cronograma'!$B$51,4,Cronograma!$J$4:'Cronograma'!$J$51) -> 0 | F8: =B8+C8+D8+E8 -> 1485000
A9: (-) Admin & Marketing | B9: =SUMIF(Cronograma!$B$4:'Cronograma'!$B$51,1,Cronograma!$F$4:'Cronograma'!$F$51)+SUMIF(Cronograma!$B$4:'Cronograma'!$B$51,1,Cronograma!$K$4:'Cronograma'!$K$51) -> 558750 | C9: =SUMIF(Cronograma!$B$4:'Cronograma'!$B$51,2,Cronograma!$F$4:'Cronograma'!$F$51)+SUMIF(Cronograma!$B$4:'Cronograma'!$B$51,2,Cronograma!$K$4:'Cronograma'!$K$51) -> 228750 | D9: =SUMIF(Cronograma!$B$4:'Cronograma'!$B$51,3,Cronograma!$F$4:'Cronograma'!$F$51)+SUMIF(Cronograma!$B$4:'Cronograma'!$B$51,3,Cronograma!$K$4:'Cronograma'!$K$51) -> 207750 | E9: =SUMIF(Cronograma!$B$4:'Cronograma'!$B$51,4,Cronograma!$F$4:'Cronograma'!$F$51)+SUMIF(Cronograma!$B$4:'Cronograma'!$B$51,4,Cronograma!$K$4:'Cronograma'!$K$51) -> 207750 | F9: =B9+C9+D9+E9 -> 1203000
A10: (-) Contingência | B10: =SUMIF(Cronograma!$B$4:'Cronograma'!$B$51,1,Cronograma!$L$4:'Cronograma'!$L$51) -> 131812.5 | C10: =SUMIF(Cronograma!$B$4:'Cronograma'!$B$51,2,Cronograma!$L$4:'Cronograma'!$L$51) -> 77062.5 | D10: =SUMIF(Cronograma!$B$4:'Cronograma'!$B$51,3,Cronograma!$L$4:'Cronograma'!$L$51) -> 25432.38 | E10: =SUMIF(Cronograma!$B$4:'Cronograma'!$B$51,4,Cronograma!$L$4:'Cronograma'!$L$51) -> 9232.38 | F10: =B10+C10+D10+E10 -> 243539.76
A11: TOTAL CUSTOS | B11: =SUMIF(Cronograma!$B$4:'Cronograma'!$B$51,1,Cronograma!$M$4:'Cronograma'!$M$51) -> 4525562.5 | C11: =SUMIF(Cronograma!$B$4:'Cronograma'!$B$51,2,Cronograma!$M$4:'Cronograma'!$M$51) -> 2645812.5 | D11: =SUMIF(Cronograma!$B$4:'Cronograma'!$B$51,3,Cronograma!$M$4:'Cronograma'!$M$51) -> 873178.38 | E11: =SUMIF(Cronograma!$B$4:'Cronograma'!$B$51,4,Cronograma!$M$4:'Cronograma'!$M$51) -> 316978.38 | F11: =B11+C11+D11+E11 -> 8361531.8
A12: Resultado Bruto | B12: =SUMIF(Cronograma!$B$4:'Cronograma'!$B$51,1,Cronograma!$N$4:'Cronograma'!$N$51) -> 255687.5 | C12: =SUMIF(Cronograma!$B$4:'Cronograma'!$B$51,2,Cronograma!$N$4:'Cronograma'!$N$51) -> 3980437.5 | D12: =SUMIF(Cronograma!$B$4:'Cronograma'!$B$51,3,Cronograma!$N$4:'Cronograma'!$N$51) -> 6023071.6 | E12: =SUMIF(Cronograma!$B$4:'Cronograma'!$B$51,4,Cronograma!$N$4:'Cronograma'!$N$51) -> 425521.62 | F12: =B12+C12+D12+E12 -> 10684718
A13: (-) Pagto. Terrenista | B13: =SUMIF(Cronograma!$B$4:'Cronograma'!$B$51,1,Cronograma!$O$4:'Cronograma'!$O$51) -> 552507.81 | C13: =SUMIF(Cronograma!$B$4:'Cronograma'!$B$51,2,Cronograma!$O$4:'Cronograma'!$O$51) -> 1393153.1 | D13: =SUMIF(Cronograma!$B$4:'Cronograma'!$B$51,3,Cronograma!$O$4:'Cronograma'!$O$51) -> 2108075.1 | E13: =SUMIF(Cronograma!$B$4:'Cronograma'!$B$51,4,Cronograma!$O$4:'Cronograma'!$O$51) -> 148932.57 | F13: =B13+C13+D13+E13 -> 4202668.6
A14: (-) Impostos | B14: =SUMIF(Cronograma!$B$4:'Cronograma'!$B$51,1,Cronograma!$Q$4:'Cronograma'!$Q$51) -> 382500 | C14: =SUMIF(Cronograma!$B$4:'Cronograma'!$B$51,2,Cronograma!$Q$4:'Cronograma'!$Q$51) -> 530100 | D14: =SUMIF(Cronograma!$B$4:'Cronograma'!$B$51,3,Cronograma!$Q$4:'Cronograma'!$Q$51) -> 551700 | E14: =SUMIF(Cronograma!$B$4:'Cronograma'!$B$51,4,Cronograma!$Q$4:'Cronograma'!$Q$51) -> 59400 | F14: =B14+C14+D14+E14 -> 1523700
A15: (-) Custo Financeiro | B15: =SUMIF(Cronograma!$B$4:'Cronograma'!$B$51,1,Cronograma!$R$4:'Cronograma'!$R$51) -> 299398.87 | C15: =SUMIF(Cronograma!$B$4:'Cronograma'!$B$51,2,Cronograma!$R$4:'Cronograma'!$R$51) -> 260434.14 | D15: =SUMIF(Cronograma!$B$4:'Cronograma'!$B$51,3,Cronograma!$R$4:'Cronograma'!$R$51) -> 2729.5342 | E15: =SUMIF(Cronograma!$B$4:'Cronograma'!$B$51,4,Cronograma!$R$4:'Cronograma'!$R$51) -> 0 | F15: =B15+C15+D15+E15 -> 562562.55
A16: FLUXO LÍQUIDO EMPREENDEDOR | B16: =SUMIF(Cronograma!$B$4:'Cronograma'!$B$51,1,Cronograma!$S$4:'Cronograma'!$S$51) -> -978719.18 | C16: =SUMIF(Cronograma!$B$4:'Cronograma'!$B$51,2,Cronograma!$S$4:'Cronograma'!$S$51) -> 1796750.2 | D16: =SUMIF(Cronograma!$B$4:'Cronograma'!$B$51,3,Cronograma!$S$4:'Cronograma'!$S$51) -> 3360567 | E16: =SUMIF(Cronograma!$B$4:'Cronograma'!$B$51,4,Cronograma!$S$4:'Cronograma'!$S$51) -> 217189.05 | F16: =B16+C16+D16+E16 -> 4395787.1
A17: SALDO ACUMULADO (final ano) | B17: =Cronograma!$T$15 -> -1978719.2 | C17: =Cronograma!$T$27 -> -181968.95 | D17: =Cronograma!$T$39 -> 3178598.1 | E17: =Cronograma!$T$51 -> 3395787.1 | F17: =Cronograma!$T$51 -> 3395787.1
A19: INDICADORES CHAVE (vínculos com Parâmetros)
A20: VGV Total | B20: =Parâmetros!$B$6 -> 22500000
A21: Preço por lote | B21: =Parâmetros!$B$4 -> 75000
A22: Total de lotes | B22: =Parâmetros!$B$5 -> 300
A23: % Empreendedor | B23: =Parâmetros!$B$18 -> 0.65
A24: % Terrenista | B24: =Parâmetros!$B$19 -> 0.35
A25: Capital próprio investido | B25: =Parâmetros!$B$21 -> 1000000
A26: Infra total | B26: =Parâmetros!$B$24 -> 7000000

Sheet Parâmetros
A1: PARÂMETROS — altere aqui e todo o fluxo de caixa recalcula
A2: 🟡 Amarelo = editável | 🔵 Azul = calculado automaticamente
A3: COMERCIAL
A4: Preço de venda por lote (R$) | B4: 75000 | C4: R$ | D4: Entrada — loteamento popular
A5: Total de lotes | B5: 300 | C5: un. | D5: Aprovado pelo projeto urbanístico
A6: VGV Total (R$) | B6: =B4*B5 -> 22500000 | C6: R$ | D6: Calculado
A7: FINANCIAMENTO
A8: % lotes à vista / banco | B8: 0.7 | D8: 70% recebido na venda
A9: % lotes financiados empreendedor | B9: =1-B8 -> 0.3 | D9: Calculado
A10: Prazo financiamento (meses) | B10: 120 | C10: meses | D10: Máximo 60 meses
A11: Parcela por lote (R$/mês) | B11: =B4*B9/B10 -> 187.5 | C11: R$/lote/mês | D11: Calculado
A12: TAXAS E PERCENTUAIS
A13: Taxa de corretagem | B13: 0.06 | C13: % venda | D13: 6% sobre valor de venda
A14: Taxa administração (% VGV) | B14: 0.03 | C14: % VGV | D14: 3% do VGV total
A15: Taxa marketing (% VGV) | B15: 0.02 | C15: % VGV | D15: 2% do VGV total
A16: Taxa contingência | B16: 0.03 | C16: % custos | D16: 3% sobre custos diretos
A17: Taxa impostos — Lucro Presumido | B17: 0.08 | C17: % receita | D17: PIS+COFINS+IRPJ+CSLL
A18: % Empreendedor | B18: 0.65 | D18: Base: lucro antes dos impostos
A19: % Terrenista | B19: =1-B18 -> 0.35 | D19: Calculado
A20: CAPITAL
A21: Capital próprio investido (R$) | B21: 1000000 | C21: R$ | D21: Aporte inicial — mês 0
A22: Taxa custo financeiro (a.m.) | B22: 0.015 | C22: a.m. | D22: 1,5% sobre saldo negativo acum.
A23: INFRAESTRUTURA
A24: Total infraestrutura (R$) | B24: 7000000 | C24: R$ | D24: Da aba Infraestrutura — pode vincular se quiser
A26: 💡 DICA: Para vincular o total da infra automaticamente, substitua o valor de B24 pela fórmula: =Viabilidade!Infraestrutura!E14 (após gerar a planilha principal)

Sheet Cronograma
A1: CRONOGRAMA MESTRE — motor de cálculo — todas as fórmulas ligadas a Parâmetros
A2: IDENTIFICAÇÃO | D2: ENTRADAS (EDITÁVEIS) | G2: RECEITAS | J2: CUSTOS | N2: RESULTADO BRUTO | Q2: RESULTADO LÍQUIDO EMPREENDEDOR
A3: MÊS | B3: ANO | C3: MÊS NOME | D3: LOTES VENDIDOS | E3: INFRA- ESTRUTURA | F3: MARKETING MENSAL | G3: RECEITA À VISTA | H3: PARCELAS RECEB. | I3: TOTAL RECEITA | J3: CORRETA- GEM | K3: ADMIN MENSAL | L3: CONTIN- GÊNCIA | M3: TOTAL CUSTOS | N3: RESULTADO BRUTO | O3: PAGTO. TERRENISTA | P3: RES.EMPREEN- DEDOR | Q3: IMPOSTOS | R3: CUSTO FINANC. | S3: FLUXO LÍQUIDO | T3: FLUXO ACUMULADO
A4: 1 | B4: =INT((A4-1)/12)+1 -> 1 | C4: Janeiro | D4: 0 | E4: 50000 | F4: 0 | G4: =D4*Parâmetros!$B$4*Parâmetros!$B$8 -> 0 | H4: 0 | I4: =G4+H4 -> 0 | J4: =D4*Parâmetros!$B$4*Parâmetros!$B$13 -> 0 | K4: =Parâmetros!$B$6*Parâmetros!$B$14/48 -> 14062.5 | L4: =(E4+F4+J4+K4)*Parâmetros!$B$16 -> 1921.875 | M4: =E4+F4+J4+K4+L4 -> 65984.375 | N4: =I4-M4 -> -65984.375 | O4: =MAX(0,N4)*Parâmetros!$B$19 -> 0 | P4: =N4-O4 -> -65984.375 | Q4: =I4*Parâmetros!$B$17 -> 0 | R4: =Parâmetros!$B$21*Parâmetros!$B$22 -> 15000 | S4: =P4-Q4-R4 -> -80984.375 | T4: =S4-Parâmetros!$B$21 -> -1080984.4
A5: 2 | B5: =INT((A5-1)/12)+1 -> 1 | C5: Fevereiro | D5: 0 | E5: 100000 | F5: 0 | G5: =D5*Parâmetros!$B$4*Parâmetros!$B$8 -> 0 | H5: =SUMPRODUCT(($D$4:D4)*($A$4:A4>=(A5-Parâmetros!$B$10)))*Parâmetros!$B$11 -> 0 | I5: =G5+H5 -> 0 | J5: =D5*Parâmetros!$B$4*Parâmetros!$B$13 -> 0 | K5: =Parâmetros!$B$6*Parâmetros!$B$14/48 -> 14062.5 | L5: =(E5+F5+J5+K5)*Parâmetros!$B$16 -> 3421.875 | M5: =E5+F5+J5+K5+L5 -> 117484.38 | N5: =I5-M5 -> -117484.38 | O5: =MAX(0,N5)*Parâmetros!$B$19 -> 0 | P5: =N5-O5 -> -117484.38 | Q5: =I5*Parâmetros!$B$17 -> 0 | R5: =MAX(0,-T4)*Parâmetros!$B$22 -> 16214.766 | S5: =P5-Q5-R5 -> -133699.14 | T5: =T4+S5 -> -1214683.5
A6: 3 | B6: =INT((A6-1)/12)+1 -> 1 | C6: Março | D6: 0 | E6: 100000 | F6: 0 | G6: =D6*Parâmetros!$B$4*Parâmetros!$B$8 -> 0 | H6: =SUMPRODUCT(($D$4:D5)*($A$4:A5>=(A6-Parâmetros!$B$10)))*Parâmetros!$B$11 -> 0 | I6: =G6+H6 -> 0 | J6: =D6*Parâmetros!$B$4*Parâmetros!$B$13 -> 0 | K6: =Parâmetros!$B$6*Parâmetros!$B$14/48 -> 14062.5 | L6: =(E6+F6+J6+K6)*Parâmetros!$B$16 -> 3421.875 | M6: =E6+F6+J6+K6+L6 -> 117484.38 | N6: =I6-M6 -> -117484.38 | O6: =MAX(0,N6)*Parâmetros!$B$19 -> 0 | P6: =N6-O6 -> -117484.38 | Q6: =I6*Parâmetros!$B$17 -> 0 | R6: =MAX(0,-T5)*Parâmetros!$B$22 -> 18220.253 | S6: =P6-Q6-R6 -> -135704.63 | T6: =T5+S6 -> -1350388.1
A7: 4 | B7: =INT((A7-1)/12)+1 -> 1 | C7: Abril | D7: 0 | E7: 200000 | F7: 0 | G7: =D7*Parâmetros!$B$4*Parâmetros!$B$8 -> 0 | H7: =SUMPRODUCT(($D$4:D6)*($A$4:A6>=(A7-Parâmetros!$B$10)))*Parâmetros!$B$11 -> 0 | I7: =G7+H7 -> 0 | J7: =D7*Parâmetros!$B$4*Parâmetros!$B$13 -> 0 | K7: =Parâmetros!$B$6*Parâmetros!$B$14/48 -> 14062.5 | L7: =(E7+F7+J7+K7)*Parâmetros!$B$16 -> 6421.875 | M7: =E7+F7+J7+K7+L7 -> 220484.38 | N7: =I7-M7 -> -220484.38 | O7: =MAX(0,N7)*Parâmetros!$B$19 -> 0 | P7: =N7-O7 -> -220484.38 | Q7: =I7*Parâmetros!$B$17 -> 0 | R7: =MAX(0,-T6)*Parâmetros!$B$22 -> 20255.822 | S7: =P7-Q7-R7 -> -240740.2 | T7: =T6+S7 -> -1591128.3
A8: 5 | B8: =INT((A8-1)/12)+1 -> 1 | C8: Maio | D8: 0 | E8: 300000 | F8: 50000 | G8: =D8*Parâmetros!$B$4*Parâmetros!$B$8 -> 0 | H8: =SUMPRODUCT(($D$4:D7)*($A$4:A7>=(A8-Parâmetros!$B$10)))*Parâmetros!$B$11 -> 0 | I8: =G8+H8 -> 0 | J8: =D8*Parâmetros!$B$4*Parâmetros!$B$13 -> 0 | K8: =Parâmetros!$B$6*Parâmetros!$B$14/48 -> 14062.5 | L8: =(E8+F8+J8+K8)*Parâmetros!$B$16 -> 10921.875 | M8: =E8+F8+J8+K8+L8 -> 374984.38 | N8: =I8-M8 -> -374984.38 | O8: =MAX(0,N8)*Parâmetros!$B$19 -> 0 | P8: =N8-O8 -> -374984.38 | Q8: =I8*Parâmetros!$B$17 -> 0 | R8: =MAX(0,-T7)*Parâmetros!$B$22 -> 23866.925 | S8: =P8-Q8-R8 -> -398851.3 | T8: =T7+S8 -> -1989979.6
A9: 6 | B9: =INT((A9-1)/12)+1 -> 1 | C9: Junho | D9: 0 | E9: 300000 | F9: 100000 | G9: =D9*Parâmetros!$B$4*Parâmetros!$B$8 -> 0 | H9: =SUMPRODUCT(($D$4:D8)*($A$4:A8>=(A9-Parâmetros!$B$10)))*Parâmetros!$B$11 -> 0 | I9: =G9+H9 -> 0 | J9: =D9*Parâmetros!$B$4*Parâmetros!$B$13 -> 0 | K9: =Parâmetros!$B$6*Parâmetros!$B$14/48 -> 14062.5 | L9: =(E9+F9+J9+K9)*Parâmetros!$B$16 -> 12421.875 | M9: =E9+F9+J9+K9+L9 -> 426484.38 | N9: =I9-M9 -> -426484.38 | O9: =MAX(0,N9)*Parâmetros!$B$19 -> 0 | P9: =N9-O9 -> -426484.38 | Q9: =I9*Parâmetros!$B$17 -> 0 | R9: =MAX(0,-T8)*Parâmetros!$B$22 -> 29849.695 | S9: =P9-Q9-R9 -> -456334.07 | T9: =T8+S9 -> -2446313.7
A10: 7 | B10: =INT((A10-1)/12)+1 -> 1 | C10: Julho | D10: 40 | E10: 400000 | F10: 100000 | G10: =D10*Parâmetros!$B$4*Parâmetros!$B$8 -> 2100000 | H10: =SUMPRODUCT(($D$4:D9)*($A$4:A9>=(A10-Parâmetros!$B$10)))*Parâmetros!$B$11 -> 0 | I10: =G10+H10 -> 2100000 | J10: =D10*Parâmetros!$B$4*Parâmetros!$B$13 -> 180000 | K10: =Parâmetros!$B$6*Parâmetros!$B$14/48 -> 14062.5 | L10: =(E10+F10+J10+K10)*Parâmetros!$B$16 -> 20821.875 | M10: =E10+F10+J10+K10+L10 -> 714884.38 | N10: =I10-M10 -> 1385115.6 | O10: =MAX(0,N10)*Parâmetros!$B$19 -> 484790.47 | P10: =N10-O10 -> 900325.16 | Q10: =I10*Parâmetros!$B$17 -> 168000 | R10: =MAX(0,-T9)*Parâmetros!$B$22 -> 36694.706 | S10: =P10-Q10-R10 -> 695630.45 | T10: =T9+S10 -> -1750683.3
A11: 8 | B11: =INT((A11-1)/12)+1 -> 1 | C11: Agosto | D11: 10 | E11: 400000 | F11: 50000 | G11: =D11*Parâmetros!$B$4*Parâmetros!$B$8 -> 525000 | H11: =SUMPRODUCT(($D$4:D10)*($A$4:A10>=(A11-Parâmetros!$B$10)))*Parâmetros!$B$11 -> 7500 | I11: =G11+H11 -> 532500 | J11: =D11*Parâmetros!$B$4*Parâmetros!$B$13 -> 45000 | K11: =Parâmetros!$B$6*Parâmetros!$B$14/48 -> 14062.5 | L11: =(E11+F11+J11+K11)*Parâmetros!$B$16 -> 15271.875 | M11: =E11+F11+J11+K11+L11 -> 524334.38 | N11: =I11-M11 -> 8165.625 | O11: =MAX(0,N11)*Parâmetros!$B$19 -> 2857.9688 | P11: =N11-O11 -> 5307.6562 | Q11: =I11*Parâmetros!$B$17 -> 42600 | R11: =MAX(0,-T10)*Parâmetros!$B$22 -> 26260.249 | S11: =P11-Q11-R11 -> -63552.593 | T11: =T10+S11 -> -1814235.9
A12: 9 | B12: =INT((A12-1)/12)+1 -> 1 | C12: Setembro | D12: 10 | E12: 400000 | F12: 30000 | G12: =D12*Parâmetros!$B$4*Parâmetros!$B$8 -> 525000 | H12: =SUMPRODUCT(($D$4:D11)*($A$4:A11>=(A12-Parâmetros!$B$10)))*Parâmetros!$B$11 -> 9375 | I12: =G12+H12 -> 534375 | J12: =D12*Parâmetros!$B$4*Parâmetros!$B$13 -> 45000 | K12: =Parâmetros!$B$6*Parâmetros!$B$14/48 -> 14062.5 | L12: =(E12+F12+J12+K12)*Parâmetros!$B$16 -> 14671.875 | M12: =E12+F12+J12+K12+L12 -> 503734.38 | N12: =I12-M12 -> 30640.625 | O12: =MAX(0,N12)*Parâmetros!$B$19 -> 10724.219 | P12: =N12-O12 -> 19916.406 | Q12: =I12*Parâmetros!$B$17 -> 42750 | R12: =MAX(0,-T11)*Parâmetros!$B$22 -> 27213.538 | S12: =P12-Q12-R12 -> -50047.132 | T12: =T11+S12 -> -1864283
A13: 10 | B13: =INT((A13-1)/12)+1 -> 1 | C13: Outubro | D13: 10 | E13: 400000 | F13: 20000 | G13: =D13*Parâmetros!$B$4*Parâmetros!$B$8 -> 525000 | H13: =SUMPRODUCT(($D$4:D12)*($A$4:A12>=(A13-Parâmetros!$B$10)))*Parâmetros!$B$11 -> 11250 | I13: =G13+H13 -> 536250 | J13: =D13*Parâmetros!$B$4*Parâmetros!$B$13 -> 45000 | K13: =Parâmetros!$B$6*Parâmetros!$B$14/48 -> 14062.5 | L13: =(E13+F13+J13+K13)*Parâmetros!$B$16 -> 14371.875 | M13: =E13+F13+J13+K13+L13 -> 493434.38 | N13: =I13-M13 -> 42815.625 | O13: =MAX(0,N13)*Parâmetros!$B$19 -> 14985.469 | P13: =N13-O13 -> 27830.156 | Q13: =I13*Parâmetros!$B$17 -> 42900 | R13: =MAX(0,-T12)*Parâmetros!$B$22 -> 27964.245 | S13: =P13-Q13-R13 -> -43034.089 | T13: =T12+S13 -> -1907317.1
A14: 11 | B14: =INT((A14-1)/12)+1 -> 1 | C14: Novembro | D14: 10 | E14: 400000 | F14: 20000 | G14: =D14*Parâmetros!$B$4*Parâmetros!$B$8 -> 525000 | H14: =SUMPRODUCT(($D$4:D13)*($A$4:A13>=(A14-Parâmetros!$B$10)))*Parâmetros!$B$11 -> 13125 | I14: =G14+H14 -> 538125 | J14: =D14*Parâmetros!$B$4*Parâmetros!$B$13 -> 45000 | K14: =Parâmetros!$B$6*Parâmetros!$B$14/48 -> 14062.5 | L14: =(E14+F14+J14+K14)*Parâmetros!$B$16 -> 14371.875 | M14: =E14+F14+J14+K14+L14 -> 493434.38 | N14: =I14-M14 -> 44690.625 | O14: =MAX(0,N14)*Parâmetros!$B$19 -> 15641.719 | P14: =N14-O14 -> 29048.906 | Q14: =I14*Parâmetros!$B$17 -> 43050 | R14: =MAX(0,-T13)*Parâmetros!$B$22 -> 28609.756 | S14: =P14-Q14-R14 -> -42610.85 | T14: =T13+S14 -> -1949927.9
A15: 12 | B15: =INT((A15-1)/12)+1 -> 1 | C15: Dezembro | D15: 10 | E15: 380000 | F15: 20000 | G15: =D15*Parâmetros!$B$4*Parâmetros!$B$8 -> 525000 | H15: =SUMPRODUCT(($D$4:D14)*($A$4:A14>=(A15-Parâmetros!$B$10)))*Parâmetros!$B$11 -> 15000 | I15: =G15+H15 -> 540000 | J15: =D15*Parâmetros!$B$4*Parâmetros!$B$13 -> 45000 | K15: =Parâmetros!$B$6*Parâmetros!$B$14/48 -> 14062.5 | L15: =(E15+F15+J15+K15)*Parâmetros!$B$16 -> 13771.875 | M15: =E15+F15+J15+K15+L15 -> 472834.38 | N15: =I15-M15 -> 67165.625 | O15: =MAX(0,N15)*Parâmetros!$B$19 -> 23507.969 | P15: =N15-O15 -> 43657.656 | Q15: =I15*Parâmetros!$B$17 -> 43200 | R15: =MAX(0,-T14)*Parâmetros!$B$22 -> 29248.919 | S15: =P15-Q15-R15 -> -28791.263 | T15: =T14+S15 -> -1978719.2
A16: 13 | B16: =INT((A16-1)/12)+1 -> 2 | C16: Janeiro | D16: 10 | E16: 350000 | F16: 5000 | G16: =D16*Parâmetros!$B$4*Parâmetros!$B$8 -> 525000 | H16: =SUMPRODUCT(($D$4:D15)*($A$4:A15>=(A16-Parâmetros!$B$10)))*Parâmetros!$B$11 -> 16875 | I16: =G16+H16 -> 541875 | J16: =D16*Parâmetros!$B$4*Parâmetros!$B$13 -> 45000 | K16: =Parâmetros!$B$6*Parâmetros!$B$14/48 -> 14062.5 | L16: =(E16+F16+J16+K16)*Parâmetros!$B$16 -> 12421.875 | M16: =E16+F16+J16+K16+L16 -> 426484.38 | N16: =I16-M16 -> 115390.62 | O16: =MAX(0,N16)*Parâmetros!$B$19 -> 40386.719 | P16: =N16-O16 -> 75003.906 | Q16: =I16*Parâmetros!$B$17 -> 43350 | R16: =MAX(0,-T15)*Parâmetros!$B$22 -> 29680.788 | S16: =P16-Q16-R16 -> 1973.1185 | T16: =T15+S16 -> -1976746.1
... A51: 48 | B51: =INT((A51-1)/12)+1 -> 4 | C51: Dezembro | D51: 0 | E51: 8333 | F51: 3250 | G51: =D51*Parâmetros!$B$4*Parâmetros!$B$8 -> 0 | H51: =SUMPRODUCT(($D$4:D50)*($A$4:A50>=(A51-Parâmetros!$B$10)))*Parâmetros!$B$11 -> 61875 | I51: =G51+H51 -> 61875 | J51: =D51*Parâmetros!$B$4*Parâmetros!$B$13 -> 0 | K51: =Parâmetros!$B$6*Parâmetros!$B$14/48 -> 14062.5 | L51: =(E51+F51+J51+K51)*Parâmetros!$B$16 -> 769.365 | M51: =E51+F51+J51+K51+L51 -> 26414.865 | N51: =I51-M51 -> 35460.135 | O51: =MAX(0,N51)*Parâmetros!$B$19 -> 12411.047 | P51: =N51-O51 -> 23049.088 | Q51: =I51*Parâmetros!$B$17 -> 4950 | R51: =MAX(0,-T50)*Parâmetros!$B$22 -> 0 | S51: =P51-Q51-R51 -> 18099.088 | T51: =T50+S51 -> 3395787.1
A52: TOTAL 48 MESES | D52: =SUM(D4:D51) -> 330 | E52: =SUM(E4:E51) -> 5429992 | F52: =SUM(F4:F51) -> 528000 | G52: =SUM(G4:G51) -> 17325000 | H52: =SUM(H4:H51) -> 1721250 | I52: =SUM(I4:I51) -> 19046250 | J52: =SUM(J4:J51) -> 1485000 | K52: =SUM(K4:K51) -> 675000 | ... S52: =SUM(S4:S51) -> 4395787.1 | T52: =T51 -> 3395787.1

Sheet Ano 1
A1: FLUXO DE CAIXA — ANO 1 — Janeiro a Dezembro — LOTEAMENTO PAPAGAIOS/MG
A2: =TEXT(SUMIF(Cronograma!$B$4:'Cronograma'!$B$51,1,Cronograma!$D$4:'Cronograma'!$D$51),"#,##0")&" lotes vendidos | Receita: "&TEXT(SUMIF(Cronograma!$B$4:'Cronograma'!$B$51,1,Cronograma!$I$4:'Cronograma'!$I$51),"R$ #,##0")&" | Fluxo Líq.: "&TEXT(SUMIF(Cronograma!$B$4:'Cronograma'!$B$51,1,Cronograma!$S$4:'Cronograma'!$S$51),"R$ #,##0") -> 90,0 lotes vendidos | Receita: R$ 4781250,0 | Fluxo Líq.: -R$ 978719,185
A3: MÊS | B3: LOTES VEND. | C3: RECEITA À VISTA | D3: PARCELAS RECEB. | E3: TOTAL RECEITA | F3: (-) INFRA- ESTR. | G3: (-) CORRE- TAGEM | H3: (-) ADMIN & MKT | I3: (-) CONTIN- GÊNC. | J3: TOTAL CUSTOS | K3: RESULT. BRUTO | L3: (-) TERR- ENISTA | M3: (-) IMPOS- TOS | N3: (-) CUSTO FINANC. | O3: FLUXO LÍQUIDO | P3: FLUXO ACUMUL.
A4: =Cronograma!C4 -> Janeiro | B4: =Cronograma!D4 -> 0 | C4: =Cronograma!G4 -> 0 | D4: =Cronograma!H4 -> 0 | E4: =Cronograma!I4 -> 0 | F4: =Cronograma!E4 -> 50000 | G4: =Cronograma!J4 -> 0 | H4: =Cronograma!F4+Cronograma!K4 -> 14062.5 | I4: =Cronograma!L4 -> 1921.875 | J4: =Cronograma!M4 -> 65984.375 | K4: =Cronograma!N4 -> -65984.375 | L4: =Cronograma!O4 -> 0 | M4: =Cronograma!Q4 -> 0 | N4: =Cronograma!R4 -> 15000 | O4: =Cronograma!S4 -> -80984.375 | P4: =Cronograma!T4 -> -1080984.4
A5: =Cronograma!C5 -> Fevereiro | B5: =Cronograma!D5 -> 0 | C5: =Cronograma!G5 -> 0 | D5: =Cronograma!H5 -> 0 | E5: =Cronograma!I5 -> 0 | F5: =Cronograma!E5 -> 100000 | G5: =Cronograma!J5 -> 0 | H5: =Cronograma!F5+Cronograma!K5 -> 14062.5 | I5: =Cronograma!L5 -> 3421.875 | J5: =Cronograma!M5 -> 117484.38 | K5: =Cronograma!N5 -> -117484.38 | L5: =Cronograma!O5 -> 0 | M5: =Cronograma!Q5 -> 0 | N5: =Cronograma!R5 -> 16214.766 | O5: =Cronograma!S5 -> -133699.14 | P5: =Cronograma!T5 -> -1214683.5
A6: =Cronograma!C6 -> Março | B6: =Cronograma!D6 -> 0 | C6: =Cronograma!G6 -> 0 | D6: =Cronograma!H6 -> 0 | E6: =Cronograma!I6 -> 0 | F6: =Cronograma!E6 -> 100000 | G6: =Cronograma!J6 -> 0 | H6: =Cronograma!F6+Cronograma!K6 -> 14062.5 | I6: =Cronograma!L6 -> 3421.875 | J6: =Cronograma!M6 -> 117484.38 | K6: =Cronograma!N6 -> -117484.38 | L6: =Cronograma!O6 -> 0 | M6: =Cronograma!Q6 -> 0 | N6: =Cronograma!R6 -> 18220.253 | O6: =Cronograma!S6 -> -135704.63 | P6: =Cronograma!T6 -> -1350388.1
A7: =Cronograma!C7 -> Abril | B7: =Cronograma!D7 -> 0 | C7: =Cronograma!G7 -> 0 | D7: =Cronograma!H7 -> 0 | E7: =Cronograma!I7 -> 0 | F7: =Cronograma!E7 -> 200000 | G7: =Cronograma!J7 -> 0 | H7: =Cronograma!F7+Cronograma!K7 -> 14062.5 | I7: =Cronograma!L7 -> 6421.875 | J7: =Cronograma!M7 -> 220484.38 | K7: =Cronograma!N7 -> -220484.38 | L7: =Cronograma!O7 -> 0 | M7: =Cronograma!Q7 -> 0 | N7: =Cronograma!R7 -> 20255.822 | O7: =Cronograma!S7 -> -240740.2 | P7: =Cronograma!T7 -> -1591128.3
A8: =Cronograma!C8 -> Maio | B8: =Cronograma!D8 -> 0 | C8: =Cronograma!G8 -> 0 | D8: =Cronograma!H8 -> 0 | E8: =Cronograma!I8 -> 0 | F8: =Cronograma!E8 -> 300000 | G8: =Cronograma!J8 -> 0 | H8: =Cronograma!F8+Cronograma!K8 -> 64062.5 | I8: =Cronograma!L8 -> 10921.875 | J8: =Cronograma!M8 -> 374984.38 | K8: =Cronograma!N8 -> -374984.38 | L8: =Cronograma!O8 -> 0 | M8: =Cronograma!Q8 -> 0 | N8: =Cronograma!R8 -> 23866.925 | O8: =Cronograma!S8 -> -398851.3 | P8: =Cronograma!T8 -> -1989979.6
A9: =Cronograma!C9 -> Junho | B9: =Cronograma!D9 -> 0 | C9: =Cronograma!G9 -> 0 | D9: =Cronograma!H9 -> 0 | E9: =Cronograma!I9 -> 0 | F9: =Cronograma!E9 -> 300000 | G9: =Cronograma!J9 -> 0 | H9: =Cronograma!F9+Cronograma!K9 -> 114062.5 | I9: =Cronograma!L9 -> 12421.875 | J9: =Cronograma!M9 -> 426484.38 | K9: =Cronograma!N9 -> -426484.38 | L9: =Cronograma!O9 -> 0 | M9: =Cronograma!Q9 -> 0 | N9: =Cronograma!R9 -> 29849.695 | O9: =Cronograma!S9 -> -456334.07 | P9: =Cronograma!T9 -> -2446313.7
A10: =Cronograma!C10 -> Julho | B10: =Cronograma!D10 -> 40 | C10: =Cronograma!G10 -> 2100000 | D10: =Cronograma!H10 -> 0 | E10: =Cronograma!I10 -> 2100000 | F10: =Cronograma!E10 -> 400000 | G10: =Cronograma!J10 -> 180000 | H10: =Cronograma!F10+Cronograma!K10 -> 114062.5 | I10: =Cronograma!L10 -> 20821.875 | J10: =Cronograma!M10 -> 714884.38 | K10: =Cronograma!N10 -> 1385115.6 | L10: =Cronograma!O10 -> 484790.47 | M10: =Cronograma!Q10 -> 168000 | N10: =Cronograma!R10 -> 36694.706 | O10: =Cronograma!S10 -> 695630.45 | P10: =Cronograma!T10 -> -1750683.3
A11: =Cronograma!C11 -> Agosto | B11: =Cronograma!D11 -> 10 | C11: =Cronograma!G11 -> 525000 | D11: =Cronograma!H11 -> 7500 | E11: =Cronograma!I11 -> 532500 | F11: =Cronograma!E11 -> 400000 | G11: =Cronograma!J11 -> 45000 | H11: =Cronograma!F11+Cronograma!K11 -> 64062.5 | I11: =Cronograma!L11 -> 15271.875 | J11: =Cronograma!M11 -> 524334.38 | K11: =Cronograma!N11 -> 8165.625 | L11: =Cronograma!O11 -> 2857.9688 | M11: =Cronograma!Q11 -> 42600 | N11: =Cronograma!R11 -> 26260.249 | O11: =Cronograma!S11 -> -63552.593 | P11: =Cronograma!T11 -> -1814235.9
A12: =Cronograma!C12 -> Setembro | B12: =Cronograma!D12 -> 10 | C12: =Cronograma!G12 -> 525000 | D12: =Cronograma!H12 -> 9375 | E12: =Cronograma!I12 -> 534375 | F12: =Cronograma!E12 -> 400000 | G12: =Cronograma!J12 -> 45000 | H12: =Cronograma!F12+Cronograma!K12 -> 44062.5 | I12: =Cronograma!L12 -> 14671.875 | J12: =Cronograma!M12 -> 503734.38 | K12: =Cronograma!N12 -> 30640.625 | L12: =Cronograma!O12 -> 10724.219 | M12: =Cronograma!Q12 -> 42750 | N12: =Cronograma!R12 -> 27213.538 | O12: =Cronograma!S12 -> -50047.132 | P12: =Cronograma!T12 -> -1864283
A13: =Cronograma!C13 -> Outubro | B13: =Cronograma!D13 -> 10 | C13: =Cronograma!G13 -> 525000 | D13: =Cronograma!H13 -> 11250 | E13: =Cronograma!I13 -> 536250 | F13: =Cronograma!E13 -> 400000 | G13: =Cronograma!J13 -> 45000 | H13: =Cronograma!F13+Cronograma!K13 -> 34062.5 | I13: =Cronograma!L13 -> 14371.875 | J13: =Cronograma!M13 -> 493434.38 | K13: =Cronograma!N13 -> 42815.625 | L13: =Cronograma!O13 -> 14985.469 | M13: =Cronograma!Q13 -> 42900 | N13: =Cronograma!R13 -> 27964.245 | O13: =Cronograma!S13 -> -43034.089 | P13: =Cronograma!T13 -> -1907317.1
A14: =Cronograma!C14 -> Novembro | B14: =Cronograma!D14 -> 10 | C14: =Cronograma!G14 -> 525000 | D14: =Cronograma!H14 -> 13125 | E14: =Cronograma!I14 -> 538125 | F14: =Cronograma!E14 -> 400000 | G14: =Cronograma!J14 -> 45000 | H14: =Cronograma!F14+Cronograma!K14 -> 34062.5 | I14: =Cronograma!L14 -> 14371.875 | J14: =Cronograma!M14 -> 493434.38 | K14: =Cronograma!N14 -> 44690.625 | L14: =Cronograma!O14 -> 15641.719 | M14: =Cronograma!Q14 -> 43050 | N14: =Cronograma!R14 -> 28609.756 | O14: =Cronograma!S14 -> -42610.85 | P14: =Cronograma!T14 -> -1949927.9
A15: =Cronograma!C15 -> Dezembro | B15: =Cronograma!D15 -> 10 | C15: =Cronograma!G15 -> 525000 | D15: =Cronograma!H15 -> 15000 | E15: =Cronograma!I15 -> 540000 | F15: =Cronograma!E15 -> 380000 | G15: =Cronograma!J15 -> 45000 | H15: =Cronograma!F15+Cronograma!K15 -> 34062.5 | I15: =Cronograma!L15 -> 13771.875 | J15: =Cronograma!M15 -> 472834.38 | K15: =Cronograma!N15 -> 67165.625 | L15: =Cronograma!O15 -> 23507.969 | M15: =Cronograma!Q15 -> 43200 | N15: =Cronograma!R15 -> 29248.919 | O15: =Cronograma!S15 -> -28791.263 | P15: =Cronograma!T15 -> -1978719.2
A16: TOTAL ANO 1 | B16: =SUM(B4:B15) -> 90 | C16: =SUM(C4:C15) -> 4725000 | D16: =SUM(D4:D15) -> 56250 | E16: =SUM(E4:E15) -> 4781250 | F16: =SUM(F4:F15) -> 3430000 | G16: =SUM(G4:G15) -> 405000 | H16: =SUM(H4:H15) -> 558750 | I16: =SUM(I4:I15) -> 131812.5 | ... O16: =SUM(O4:O15) -> -978719.18 | P16: =Cronograma!T15 -> -1978719.2
A18: 📌 Todos os valores são fórmulas vinculadas à aba Cronograma, que por sua vez vincula com Parâmetros. Para alterar qualquer premissa, edite apenas a aba Parâmetros.

Sheet Ano 2
A1: FLUXO DE CAIXA — ANO 2 — Janeiro a Dezembro — LOTEAMENTO PAPAGAIOS/MG
A2: =TEXT(SUMIF(Cronograma!$B$4:'Cronograma'!$B$51,2,Cronograma!$D$4:'Cronograma'!$D$51),"#,##0")&" lotes vendidos | Receita: "&TEXT(SUMIF(Cronograma!$B$4:'Cronograma'!$B$51,2,Cronograma!$I$4:'Cronograma'!$I$51),"R$ #,##0")&" | Fluxo Líq.: "&TEXT(SUMIF(Cronograma!$B$4:'Cronograma'!$B$51,2,Cronograma!$S$4:'Cronograma'!$S$51),"R$ #,##0") -> 120,0 lotes vendidos | Receita: R$ 6626250,0 | Fluxo Líq.: R$ 1796750,236
A3: MÊS | B3: LOTES VEND. | C3: RECEITA À VISTA | D3: PARCELAS RECEB. | E3: TOTAL RECEITA | F3: (-) INFRA- ESTR. | G3: (-) CORRE- TAGEM | H3: (-) ADMIN & MKT | I3: (-) CONTIN- GÊNC. | J3: TOTAL CUSTOS | K3: RESULT. BRUTO | L3: (-) TERR- ENISTA | M3: (-) IMPOS- TOS | N3: (-) CUSTO FINANC. | O3: FLUXO LÍQUIDO | P3: FLUXO ACUMUL.
A4: =Cronograma!C16 -> Janeiro | B4: =Cronograma!D16 -> 10 | C4: =Cronograma!G16 -> 525000 | D4: =Cronograma!H16 -> 16875 | E4: =Cronograma!I16 -> 541875 | F4: =Cronograma!E16 -> 350000 | G4: =Cronograma!J16 -> 45000 | H4: =Cronograma!F16+Cronograma!K16 -> 19062.5 | I4: =Cronograma!L16 -> 12421.875 | J4: =Cronograma!M16 -> 426484.38 | K4: =Cronograma!N16 -> 115390.62 | L4: =Cronograma!O16 -> 40386.719 | M4: =Cronograma!Q16 -> 43350 | N4: =Cronograma!R16 -> 29680.788 | O4: =Cronograma!S16 -> 1973.1185 | P4: =Cronograma!T16 -> -1976746.1
A5: =Cronograma!C17 -> Fevereiro | B5: =Cronograma!D17 -> 10 | C5: =Cronograma!G17 -> 525000 | D5: =Cronograma!H17 -> 18750 | E5: =Cronograma!I17 -> 543750 | F5: =Cronograma!E17 -> 350000 | G5: =Cronograma!J17 -> 45000 | H5: =Cronograma!F17+Cronograma!K17 -> 19062.5 | I5: =Cronograma!L17 -> 12421.875 | J5: =Cronograma!M17 -> 426484.38 | K5: =Cronograma!N17 -> 117265.62 | L5: =Cronograma!O17 -> 41042.969 | M5: =Cronograma!Q17 -> 43500 | N5: =Cronograma!R17 -> 29651.191 | O5: =Cronograma!S17 -> 3071.4653 | P5: =Cronograma!T17 -> -1973674.6
A6: =Cronograma!C18 -> Março | B6: =Cronograma!D18 -> 10 | C6: =Cronograma!G18 -> 525000 | D6: =Cronograma!H18 -> 20625 | E6: =Cronograma!I18 -> 545625 | F6: =Cronograma!E18 -> 300000 | G6: =Cronograma!J18 -> 45000 | H6: =Cronograma!F18+Cronograma!K18 -> 19062.5 | I6: =Cronograma!L18 -> 10921.875 | J6: =Cronograma!M18 -> 374984.38 | K6: =Cronograma!N18 -> 170640.62 | L6: =Cronograma!O18 -> 59724.219 | M6: =Cronograma!Q18 -> 43650 | N6: =Cronograma!R18 -> 29605.119 | O6: =Cronograma!S18 -> 37661.287 | P6: =Cronograma!T18 -> -1936013.3
A7: =Cronograma!C19 -> Abril | B7: =Cronograma!D19 -> 10 | C7: =Cronograma!G19 -> 525000 | D7: =Cronograma!H19 -> 22500 | E7: =Cronograma!I19 -> 547500 | F7: =Cronograma!E19 -> 200000 | G7: =Cronograma!J19 -> 45000 | H7: =Cronograma!F19+Cronograma!K19 -> 19062.5 | I7: =Cronograma!L19 -> 7921.875 | J7: =Cronograma!M19 -> 271984.38 | K7: =Cronograma!N19 -> 275515.62 | L7: =Cronograma!O19 -> 96430.469 | M7: =Cronograma!Q19 -> 43800 | N7: =Cronograma!R19 -> 29040.2 | O7: =Cronograma!S19 -> 106244.96 | P7: =Cronograma!T19 -> -1829768.4
A8: =Cronograma!C20 -> Maio | B8: =Cronograma!D20 -> 10 | C8: =Cronograma!G20 -> 525000 | D8: =Cronograma!H20 -> 24375 | E8: =Cronograma!I20 -> 549375 | F8: =Cronograma!E20 -> 150000 | G8: =Cronograma!J20 -> 45000 | H8: =Cronograma!F20+Cronograma!K20 -> 19062.5 | I8: =Cronograma!L20 -> 6421.875 | J8: =Cronograma!M20 -> 220484.38 | K8: =Cronograma!N20 -> 328890.62 | L8: =Cronograma!O20 -> 115111.72 | M8: =Cronograma!Q20 -> 43950 | N8: =Cronograma!R20 -> 27446.525 | O8: =Cronograma!S20 -> 142382.38 | P8: =Cronograma!T20 -> -1687386
A9: =Cronograma!C21 -> Junho | B9: =Cronograma!D21 -> 10 | C9: =Cronograma!G21 -> 525000 | D9: =Cronograma!H21 -> 26250 | E9: =Cronograma!I21 -> 551250 | F9: =Cronograma!E21 -> 100000 | G9: =Cronograma!J21 -> 45000 | H9: =Cronograma!F21+Cronograma!K21 -> 19062.5 | I9: =Cronograma!L21 -> 4921.875 | J9: =Cronograma!M21 -> 168984.38 | K9: =Cronograma!N21 -> 382265.62 | L9: =Cronograma!O21 -> 133792.97 | M9: =Cronograma!Q21 -> 44100 | N9: =Cronograma!R21 -> 25310.79 | O9: =Cronograma!S21 -> 179061.87 | P9: =Cronograma!T21 -> -1508324.1
A10: =Cronograma!C22 -> Julho | B10: =Cronograma!D22 -> 10 | C10: =Cronograma!G22 -> 525000 | D10: =Cronograma!H22 -> 28125 | E10: =Cronograma!I22 -> 553125 | F10: =Cronograma!E22 -> 100000 | G10: =Cronograma!J22 -> 45000 | H10: =Cronograma!F22+Cronograma!K22 -> 19062.5 | I10: =Cronograma!L22 -> 4921.875 | J10: =Cronograma!M22 -> 168984.38 | K10: =Cronograma!N22 -> 384140.62 | L10: =Cronograma!O22 -> 134449.22 | M10: =Cronograma!Q22 -> 44250 | N10: =Cronograma!R22 -> 22624.862 | O10: =Cronograma!S22 -> 182816.54 | P10: =Cronograma!T22 -> -1325507.6
A11: =Cronograma!C23 -> Agosto | B11: =Cronograma!D23 -> 10 | C11: =Cronograma!G23 -> 525000 | D11: =Cronograma!H23 -> 30000 | E11: =Cronograma!I23 -> 555000 | F11: =Cronograma!E23 -> 80000 | G11: =Cronograma!J23 -> 45000 | H11: =Cronograma!F23+Cronograma!K23 -> 19062.5 | I11: =Cronograma!L23 -> 4321.875 | J11: =Cronograma!M23 -> 148384.38 | K11: =Cronograma!N23 -> 406615.62 | L11: =Cronograma!O23 -> 142315.47 | M11: =Cronograma!Q23 -> 44400 | N11: =Cronograma!R23 -> 19882.613 | O11: =Cronograma!S23 -> 200017.54 | P11: =Cronograma!T23 -> -1125490
A12: =Cronograma!C24 -> Setembro | B12: =Cronograma!D24 -> 10 | C12: =Cronograma!G24 -> 525000 | D12: =Cronograma!H24 -> 31875 | E12: =Cronograma!I24 -> 556875 | F12: =Cronograma!E24 -> 60000 | G12: =Cronograma!J24 -> 45000 | H12: =Cronograma!F24+Cronograma!K24 -> 19062.5 | I12: =Cronograma!L24 -> 3721.875 | J12: =Cronograma!M24 -> 127784.38 | K12: =Cronograma!N24 -> 429090.62 | L12: =Cronograma!O24 -> 150181.72 | M12: =Cronograma!Q24 -> 44550 | N12: =Cronograma!R24 -> 16882.35 | O12: =Cronograma!S24 -> 217476.56 | P12: =Cronograma!T24 -> -908013.47
A13: =Cronograma!C25 -> Outubro | B13: =Cronograma!D25 -> 10 | C13: =Cronograma!G25 -> 525000 | D13: =Cronograma!H25 -> 33750 | E13: =Cronograma!I25 -> 558750 | F13: =Cronograma!E25 -> 50000 | G13: =Cronograma!J25 -> 45000 | H13: =Cronograma!F25+Cronograma!K25 -> 19062.5 | I13: =Cronograma!L25 -> 3421.875 | J13: =Cronograma!M25 -> 117484.38 | K13: =Cronograma!N25 -> 441265.62 | L13: =Cronograma!O25 -> 154442.97 | M13: =Cronograma!Q25 -> 44700 | N13: =Cronograma!R25 -> 13620.202 | O13: =Cronograma!S25 -> 228502.45 | P13: =Cronograma!T25 -> -679511.01
A14: =Cronograma!C26 -> Novembro | B14: =Cronograma!D26 -> 10 | C14: =Cronograma!G26 -> 525000 | D14: =Cronograma!H26 -> 35625 | E14: =Cronograma!I26 -> 560625 | F14: =Cronograma!E26 -> 30000 | G14: =Cronograma!J26 -> 45000 | H14: =Cronograma!F26+Cronograma!K26 -> 19062.5 | I14: =Cronograma!L26 -> 2821.875 | J14: =Cronograma!M26 -> 96884.375 | K14: =Cronograma!N26 -> 463740.62 | L14: =Cronograma!O26 -> 162309.22 | M14: =Cronograma!Q26 -> 44850 | N14: =Cronograma!R26 -> 10192.665 | O14: =Cronograma!S26 -> 246388.74 | P14: =Cronograma!T26 -> -433122.27
A15: =Cronograma!C27 -> Dezembro | B15: =Cronograma!D27 -> 10 | C15: =Cronograma!G27 -> 525000 | D15: =Cronograma!H27 -> 37500 | E15: =Cronograma!I27 -> 562500 | F15: =Cronograma!E27 -> 30000 | G15: =Cronograma!J27 -> 45000 | H15: =Cronograma!F27+Cronograma!K27 -> 19062.5 | I15: =Cronograma!L27 -> 2821.875 | J15: =Cronograma!M27 -> 96884.375 | K15: =Cronograma!N27 -> 465615.62 | L15: =Cronograma!O27 -> 162965.47 | M15: =Cronograma!Q27 -> 45000 | N15: =Cronograma!R27 -> 6496.8341 | O15: =Cronograma!S27 -> 251153.32 | P15: =Cronograma!T27 -> -181968.95
A16: TOTAL ANO 2 | B16: =SUM(B4:B15) -> 120 | C16: =SUM(C4:C15) -> 6300000 | D16: =SUM(D4:D15) -> 326250 | E16: =SUM(E4:E15) -> 6626250 | F16: =SUM(F4:F15) -> 1800000 | G16: =SUM(G4:G15) -> 540000 | H16: =SUM(H4:H15) -> 228750 | I16: =SUM(I4:I15) -> 77062.5 | ... O16: =SUM(O4:O15) -> 1796750.2 | P16: =Cronograma!T27 -> -181968.95
A18: 📌 Todos os valores são fórmulas vinculadas à aba Cronograma, que por sua vez vincula com Parâmetros. Para alterar qualquer premissa, edite apenas a aba Parâmetros.

Sheet Ano 3
A1: FLUXO DE CAIXA — ANO 3 — Janeiro a Dezembro — LOTEAMENTO PAPAGAIOS/MG
A2: =TEXT(SUMIF(Cronograma!$B$4:'Cronograma'!$B$51,3,Cronograma!$D$4:'Cronograma'!$D$51),"#,##0")&" lotes vendidos | Receita: "&TEXT(SUMIF(Cronograma!$B$4:'Cronograma'!$B$51,3,Cronograma!$I$4:'Cronograma'!$I$51),"R$ #,##0")&" | Fluxo Líq.: "&TEXT(SUMIF(Cronograma!$B$4:'Cronograma'!$B$51,3,Cronograma!$S$4:'Cronograma'!$S$51),"R$ #,##0") -> 120,0 lotes vendidos | Receita: R$ 6896250,0 | Fluxo Líq.: R$ 3360567,019
A3: MÊS | B3: LOTES VEND. | C3: RECEITA À VISTA | D3: PARCELAS RECEB. | E3: TOTAL RECEITA | F3: (-) INFRA- ESTR. | G3: (-) CORRE- TAGEM | H3: (-) ADMIN & MKT | I3: (-) CONTIN- GÊNC. | J3: TOTAL CUSTOS | K3: RESULT. BRUTO | L3: (-) TERR- ENISTA | M3: (-) IMPOS- TOS | N3: (-) CUSTO FINANC. | O3: FLUXO LÍQUIDO | P3: FLUXO ACUMUL.
A4: =Cronograma!C28 -> Janeiro | B4: =Cronograma!D28 -> 10 | C4: =Cronograma!G28 -> 525000 | D4: =Cronograma!H28 -> 39375 | E4: =Cronograma!I28 -> 564375 | F4: =Cronograma!E28 -> 8333 | G4: =Cronograma!J28 -> 45000 | H4: =Cronograma!F28+Cronograma!K28 -> 17312.5 | I4: =Cronograma!L28 -> 2119.365 | J4: =Cronograma!M28 -> 72764.865 | K4: =Cronograma!N28 -> 491610.14 | L4: =Cronograma!O28 -> 172063.55 | M4: =Cronograma!Q28 -> 45150 | N4: =Cronograma!R28 -> 2729.5342 | O4: =Cronograma!S28 -> 271667.05 | P4: =Cronograma!T28 -> 89698.105
A5: =Cronograma!C29 -> Fevereiro | B5: =Cronograma!D29 -> 10 | C5: =Cronograma!G29 -> 525000 | D5: =Cronograma!H29 -> 41250 | E5: =Cronograma!I29 -> 566250 | F5: =Cronograma!E29 -> 8333 | G5: =Cronograma!J29 -> 45000 | H5: =Cronograma!F29+Cronograma!K29 -> 17312.5 | I5: =Cronograma!L29 -> 2119.365 | J5: =Cronograma!M29 -> 72764.865 | K5: =Cronograma!N29 -> 493485.14 | L5: =Cronograma!O29 -> 172719.8 | M5: =Cronograma!Q29 -> 45300 | N5: =Cronograma!R29 -> 0 | O5: =Cronograma!S29 -> 275465.34 | P5: =Cronograma!T29 -> 365163.44
A6: =Cronograma!C30 -> Março | B6: =Cronograma!D30 -> 10 | C6: =Cronograma!G30 -> 525000 | D6: =Cronograma!H30 -> 43125 | E6: =Cronograma!I30 -> 568125 | F6: =Cronograma!E30 -> 8333 | G6: =Cronograma!J30 -> 45000 | H6: =Cronograma!F30+Cronograma!K30 -> 17312.5 | I6: =Cronograma!L30 -> 2119.365 | J6: =Cronograma!M30 -> 72764.865 | K6: =Cronograma!N30 -> 495360.14 | L6: =Cronograma!O30 -> 173376.05 | M6: =Cronograma!Q30 -> 45450 | N6: =Cronograma!R30 -> 0 | O6: =Cronograma!S30 -> 276534.09 | P6: =Cronograma!T30 -> 641697.53
A7: =Cronograma!C31 -> Abril | B7: =Cronograma!D31 -> 10 | C7: =Cronograma!G31 -> 525000 | D7: =Cronograma!H31 -> 45000 | E7: =Cronograma!I31 -> 570000 | F7: =Cronograma!E31 -> 8333 | G7: =Cronograma!J31 -> 45000 | H7: =Cronograma!F31+Cronograma!K31 -> 17312.5 | I7: =Cronograma!L31 -> 2119.365 | J7: =Cronograma!M31 -> 72764.865 | K7: =Cronograma!N31 -> 497235.14 | L7: =Cronograma!O31 -> 174032.3 | M7: =Cronograma!Q31 -> 45600 | N7: =Cronograma!R31 -> 0 | O7: =Cronograma!S31 -> 277602.84 | P7: =Cronograma!T31 -> 919300.37
A8: =Cronograma!C32 -> Maio | B8: =Cronograma!D32 -> 10 | C8: =Cronograma!G32 -> 525000 | D8: =Cronograma!H32 -> 46875 | E8: =Cronograma!I32 -> 571875 | F8: =Cronograma!E32 -> 8333 | G8: =Cronograma!J32 -> 45000 | H8: =Cronograma!F32+Cronograma!K32 -> 17312.5 | I8: =Cronograma!L32 -> 2119.365 | J8: =Cronograma!M32 -> 72764.865 | K8: =Cronograma!N32 -> 499110.14 | L8: =Cronograma!O32 -> 174688.55 | M8: =Cronograma!Q32 -> 45750 | N8: =Cronograma!R32 -> 0 | O8: =Cronograma!S32 -> 278671.59 | P8: =Cronograma!T32 -> 1197972
A9: =Cronograma!C33 -> Junho | B9: =Cronograma!D33 -> 10 | C9: =Cronograma!G33 -> 525000 | D9: =Cronograma!H33 -> 48750 | E9: =Cronograma!I33 -> 573750 | F9: =Cronograma!E33 -> 8333 | G9: =Cronograma!J33 -> 45000 | H9: =Cronograma!F33+Cronograma!K33 -> 17312.5 | I9: =Cronograma!L33 -> 2119.365 | J9: =Cronograma!M33 -> 72764.865 | K9: =Cronograma!N33 -> 500985.14 | L9: =Cronograma!O33 -> 175344.8 | M9: =Cronograma!Q33 -> 45900 | N9: =Cronograma!R33 -> 0 | O9: =Cronograma!S33 -> 279740.34 | P9: =Cronograma!T33 -> 1477712.3
A10: =Cronograma!C34 -> Julho | B10: =Cronograma!D34 -> 10 | C10: =Cronograma!G34 -> 525000 | D10: =Cronograma!H34 -> 50625 | E10: =Cronograma!I34 -> 575625 | F10: =Cronograma!E34 -> 8333 | G10: =Cronograma!J34 -> 45000 | H10: =Cronograma!F34+Cronograma!K34 -> 17312.5 | I10: =Cronograma!L34 -> 2119.365 | J10: =Cronograma!M34 -> 72764.865 | K10: =Cronograma!N34 -> 502860.14 | L10: =Cronograma!O34 -> 176001.05 | M10: =Cronograma!Q34 -> 46050 | N10: =Cronograma!R34 -> 0 | O10: =Cronograma!S34 -> 280809.09 | P10: =Cronograma!T34 -> 1758521.4
A11: =Cronograma!C35 -> Agosto | B11: =Cronograma!D35 -> 10 | C11: =Cronograma!G35 -> 525000 | D11: =Cronograma!H35 -> 52500 | E11: =Cronograma!I35 -> 577500 | F11: =Cronograma!E35 -> 8333 | G11: =Cronograma!J35 -> 45000 | H11: =Cronograma!F35+Cronograma!K35 -> 17312.5 | I11: =Cronograma!L35 -> 2119.365 | J11: =Cronograma!M35 -> 72764.865 | K11: =Cronograma!N35 -> 504735.14 | L11: =Cronograma!O35 -> 176657.3 | M11: =Cronograma!Q35 -> 46200 | N11: =Cronograma!R35 -> 0 | O11: =Cronograma!S35 -> 281877.84 | P11: =Cronograma!T35 -> 2040399.2
A12: =Cronograma!C36 -> Setembro | B12: =Cronograma!D36 -> 10 | C12: =Cronograma!G36 -> 525000 | D12: =Cronograma!H36 -> 54375 | E12: =Cronograma!I36 -> 579375 | F12: =Cronograma!E36 -> 8333 | G12: =Cronograma!J36 -> 45000 | H12: =Cronograma!F36+Cronograma!K36 -> 17312.5 | I12: =Cronograma!L36 -> 2119.365 | J12: =Cronograma!M36 -> 72764.865 | K12: =Cronograma!N36 -> 506610.14 | L12: =Cronograma!O36 -> 177313.55 | M12: =Cronograma!Q36 -> 46350 | N12: =Cronograma!R36 -> 0 | O12: =Cronograma!S36 -> 282946.59 | P12: =Cronograma!T36 -> 2323345.8
A13: =Cronograma!C37 -> Outubro | B13: =Cronograma!D37 -> 10 | C13: =Cronograma!G37 -> 525000 | D13: =Cronograma!H37 -> 56250 | E13: =Cronograma!I37 -> 581250 | F13: =Cronograma!E37 -> 8333 | G13: =Cronograma!J37 -> 45000 | H13: =Cronograma!F37+Cronograma!K37 -> 17312.5 | I13: =Cronograma!L37 -> 2119.365 | J13: =Cronograma!M37 -> 72764.865 | K13: =Cronograma!N37 -> 508485.14 | L13: =Cronograma!O37 -> 177969.8 | M13: =Cronograma!Q37 -> 46500 | N13: =Cronograma!R37 -> 0 | O13: =Cronograma!S37 -> 284015.34 | P13: =Cronograma!T37 -> 2607361.1
A14: =Cronograma!C38 -> Novembro | B14: =Cronograma!D38 -> 10 | C14: =Cronograma!G38 -> 525000 | D14: =Cronograma!H38 -> 58125 | E14: =Cronograma!I38 -> 583125 | F14: =Cronograma!E38 -> 8333 | G14: =Cronograma!J38 -> 45000 | H14: =Cronograma!F38+Cronograma!K38 -> 17312.5 | I14: =Cronograma!L38 -> 2119.365 | J14: =Cronograma!M38 -> 72764.865 | K14: =Cronograma!N38 -> 510360.14 | L14: =Cronograma!O38 -> 178626.05 | M14: =Cronograma!Q38 -> 46650 | N14: =Cronograma!R38 -> 0 | O14: =Cronograma!S38 -> 285084.09 | P14: =Cronograma!T38 -> 2892445.2
A15: =Cronograma!C39 -> Dezembro | B15: =Cronograma!D39 -> 10 | C15: =Cronograma!G39 -> 525000 | D15: =Cronograma!H39 -> 60000 | E15: =Cronograma!I39 -> 585000 | F15: =Cronograma!E39 -> 8333 | G15: =Cronograma!J39 -> 45000 | H15: =Cronograma!F39+Cronograma!K39 -> 17312.5 | I15: =Cronograma!L39 -> 2119.365 | J15: =Cronograma!M39 -> 72764.865 | K15: =Cronograma!N39 -> 512235.14 | L15: =Cronograma!O39 -> 179282.3 | M15: =Cronograma!Q39 -> 46800 | N15: =Cronograma!R39 -> 0 | O15: =Cronograma!S39 -> 286152.84 | P15: =Cronograma!T39 -> 3178598.1
A16: TOTAL ANO 3 | B16: =SUM(B4:B15) -> 120 | C16: =SUM(C4:C15) -> 6300000 | D16: =SUM(D4:D15) -> 596250 | E16: =SUM(E4:E15) -> 6896250 | F16: =SUM(F4:F15) -> 99996 | G16: =SUM(G4:G15) -> 540000 | H16: =SUM(H4:H15) -> 207750 | I16: =SUM(I4:I15) -> 25432.38 | ... O16: =SUM(O4:O15) -> 3360567 | P16: =Cronograma!T39 -> 3178598.1
A18: 📌 Todos os valores são fórmulas vinculadas à aba Cronograma, que por sua vez vincula com Parâmetros. Para alterar qualquer premissa, edite apenas a aba Parâmetros.

Sheet Ano 4
A1: FLUXO DE CAIXA — ANO 4 — Janeiro a Dezembro — LOTEAMENTO PAPAGAIOS/MG
A2: =TEXT(SUMIF(Cronograma!$B$4:'Cronograma'!$B$51,4,Cronograma!$D$4:'Cronograma'!$D$51),"#,##0")&" lotes vendidos | Receita: "&TEXT(SUMIF(Cronograma!$B$4:'Cronograma'!$B$51,4,Cronograma!$I$4:'Cronograma'!$I$51),"R$ #,##0")&" | Fluxo Líq.: "&TEXT(SUMIF(Cronograma!$B$4:'Cronograma'!$B$51,4,Cronograma!$S$4:'Cronograma'!$S$51),"R$ #,##0") -> ,0 lotes vendidos | Receita: R$ 742500,0 | Fluxo Líq.: R$ 217189,053
A3: MÊS | B3: LOTES VEND. | C3: RECEITA À VISTA | D3: PARCELAS RECEB. | E3: TOTAL RECEITA | F3: (-) INFRA- ESTR. | G3: (-) CORRE- TAGEM | H3: (-) ADMIN & MKT | I3: (-) CONTIN- GÊNC. | J3: TOTAL CUSTOS | K3: RESULT. BRUTO | L3: (-) TERR- ENISTA | M3: (-) IMPOS- TOS | N3: (-) CUSTO FINANC. | O3: FLUXO LÍQUIDO | P3: FLUXO ACUMUL.
A4: =Cronograma!C40 -> Janeiro | B4: =Cronograma!D40 -> 0 | C4: =Cronograma!G40 -> 0 | D4: =Cronograma!H40 -> 61875 | E4: =Cronograma!I40 -> 61875 | F4: =Cronograma!E40 -> 8333 | G4: =Cronograma!J40 -> 0 | H4: =Cronograma!F40+Cronograma!K40 -> 17312.5 | I4: =Cronograma!L40 -> 769.365 | J4: =Cronograma!M40 -> 26414.865 | K4: =Cronograma!N40 -> 35460.135 | L4: =Cronograma!O40 -> 12411.047 | M4: =Cronograma!Q40 -> 4950 | N4: =Cronograma!R40 -> 0 | O4: =Cronograma!S40 -> 18099.088 | P4: =Cronograma!T40 -> 3196697.2
A5: =Cronograma!C41 -> Fevereiro | B5: =Cronograma!D41 -> 0 | C5: =Cronograma!G41 -> 0 | D5: =Cronograma!H41 -> 61875 | E5: =Cronograma!I41 -> 61875 | F5: =Cronograma!E41 -> 8333 | G5: =Cronograma!J41 -> 0 | H5: =Cronograma!F41+Cronograma!K41 -> 17312.5 | I5: =Cronograma!L41 -> 769.365 | J5: =Cronograma!M41 -> 26414.865 | K5: =Cronograma!N41 -> 35460.135 | L5: =Cronograma!O41 -> 12411.047 | M5: =Cronograma!Q41 -> 4950 | N5: =Cronograma!R41 -> 0 | O5: =Cronograma!S41 -> 18099.088 | P5: =Cronograma!T41 -> 3214796.2
A6: =Cronograma!C42 -> Março | B6: =Cronograma!D42 -> 0 | C6: =Cronograma!G42 -> 0 | D6: =Cronograma!H42 -> 61875 | E6: =Cronograma!I42 -> 61875 | F6: =Cronograma!E42 -> 8333 | G6: =Cronograma!J42 -> 0 | H6: =Cronograma!F42+Cronograma!K42 -> 17312.5 | I6: =Cronograma!L42 -> 769.365 | J6: =Cronograma!M42 -> 26414.865 | K6: =Cronograma!N42 -> 35460.135 | L6: =Cronograma!O42 -> 12411.047 | M6: =Cronograma!Q42 -> 4950 | N6: =Cronograma!R42 -> 0 | O6: =Cronograma!S42 -> 18099.088 | P6: =Cronograma!T42 -> 3232895.3
A7: =Cronograma!C43 -> Abril | B7: =Cronograma!D43 -> 0 | C7: =Cronograma!G43 -> 0 | D7: =Cronograma!H43 -> 61875 | E7: =Cronograma!I43 -> 61875 | F7: =Cronograma!E43 -> 8333 | G7: =Cronograma!J43 -> 0 | H7: =Cronograma!F43+Cronograma!K43 -> 17312.5 | I7: =Cronograma!L43 -> 769.365 | J7: =Cronograma!M43 -> 26414.865 | K7: =Cronograma!N43 -> 35460.135 | L7: =Cronograma!O43 -> 12411.047 | M7: =Cronograma!Q43 -> 4950 | N7: =Cronograma!R43 -> 0 | O7: =Cronograma!S43 -> 18099.088 | P7: =Cronograma!T43 -> 3250994.4
A8: =Cronograma!C44 -> Maio | B8: =Cronograma!D44 -> 0 | C8: =Cronograma!G44 -> 0 | D8: =Cronograma!H44 -> 61875 | E8: =Cronograma!I44 -> 61875 | F8: =Cronograma!E44 -> 8333 | G8: =Cronograma!J44 -> 0 | H8: =Cronograma!F44+Cronograma!K44 -> 17312.5 | I8: =Cronograma!L44 -> 769.365 | J8: =Cronograma!M44 -> 26414.865 | K8: =Cronograma!N44 -> 35460.135 | L8: =Cronograma!O44 -> 12411.047 | M8: =Cronograma!Q44 -> 4950 | N8: =Cronograma!R44 -> 0 | O8: =Cronograma!S44 -> 18099.088 | P8: =Cronograma!T44 -> 3269093.5
A9: =Cronograma!C45 -> Junho | B9: =Cronograma!D45 -> 0 | C9: =Cronograma!G45 -> 0 | D9: =Cronograma!H45 -> 61875 | E9: =Cronograma!I45 -> 61875 | F9: =Cronograma!E45 -> 8333 | G9: =Cronograma!J45 -> 0 | H9: =Cronograma!F45+Cronograma!K45 -> 17312.5 | I9: =Cronograma!L45 -> 769.365 | J9: =Cronograma!M45 -> 26414.865 | K9: =Cronograma!N45 -> 35460.135 | L9: =Cronograma!O45 -> 12411.047 | M9: =Cronograma!Q45 -> 4950 | N9: =Cronograma!R45 -> 0 | O9: =Cronograma!S45 -> 18099.088 | P9: =Cronograma!T45 -> 3287192.6
A10: =Cronograma!C46 -> Julho | B10: =Cronograma!D46 -> 0 | C10: =Cronograma!G46 -> 0 | D10: =Cronograma!H46 -> 61875 | E10: =Cronograma!I46 -> 61875 | F10: =Cronograma!E46 -> 8333 | G10: =Cronograma!J46 -> 0 | H10: =Cronograma!F46+Cronograma!K46 -> 17312.5 | I10: =Cronograma!L46 -> 769.365 | J10: =Cronograma!M46 -> 26414.865 | K10: =Cronograma!N46 -> 35460.135 | L10: =Cronograma!O46 -> 12411.047 | M10: =Cronograma!Q46 -> 4950 | N10: =Cronograma!R46 -> 0 | O10: =Cronograma!S46 -> 18099.088 | P10: =Cronograma!T46 -> 3305291.7
A11: =Cronograma!C47 -> Agosto | B11: =Cronograma!D47 -> 0 | C11: =Cronograma!G47 -> 0 | D11: =Cronograma!H47 -> 61875 | E11: =Cronograma!I47 -> 61875 | F11: =Cronograma!E47 -> 8333 | G11: =Cronograma!J47 -> 0 | H11: =Cronograma!F47+Cronograma!K47 -> 17312.5 | I11: =Cronograma!L47 -> 769.365 | J11: =Cronograma!M47 -> 26414.865 | K11: =Cronograma!N47 -> 35460.135 | L11: =Cronograma!O47 -> 12411.047 | M11: =Cronograma!Q47 -> 4950 | N11: =Cronograma!R47 -> 0 | O11: =Cronograma!S47 -> 18099.088 | P11: =Cronograma!T47 -> 3323390.8
A12: =Cronograma!C48 -> Setembro | B12: =Cronograma!D48 -> 0 | C12: =Cronograma!G48 -> 0 | D12: =Cronograma!H48 -> 61875 | E12: =Cronograma!I48 -> 61875 | F12: =Cronograma!E48 -> 8333 | G12: =Cronograma!J48 -> 0 | H12: =Cronograma!F48+Cronograma!K48 -> 17312.5 | I12: =Cronograma!L48 -> 769.365 | J12: =Cronograma!M48 -> 26414.865 | K12: =Cronograma!N48 -> 35460.135 | L12: =Cronograma!O48 -> 12411.047 | M12: =Cronograma!Q48 -> 4950 | N12: =Cronograma!R48 -> 0 | O12: =Cronograma!S48 -> 18099.088 | P12: =Cronograma!T48 -> 3341489.9
A13: =Cronograma!C49 -> Outubro | B13: =Cronograma!D49 -> 0 | C13: =Cronograma!G49 -> 0 | D13: =Cronograma!H49 -> 61875 | E13: =Cronograma!I49 -> 61875 | F13: =Cronograma!E49 -> 8333 | G13: =Cronograma!J49 -> 0 | H13: =Cronograma!F49+Cronograma!K49 -> 17312.5 | I13: =Cronograma!L49 -> 769.365 | J13: =Cronograma!M49 -> 26414.865 | K13: =Cronograma!N49 -> 35460.135 | L13: =Cronograma!O49 -> 12411.047 | M13: =Cronograma!Q49 -> 4950 | N13: =Cronograma!R49 -> 0 | O13: =Cronograma!S49 -> 18099.088 | P13: =Cronograma!T49 -> 3359588.9
A14: =Cronograma!C50 -> Novembro | B14: =Cronograma!D50 -> 0 | C14: =Cronograma!G50 -> 0 | D14: =Cronograma!H50 -> 61875 | E14: =Cronograma!I50 -> 61875 | F14: =Cronograma!E50 -> 8333 | G14: =Cronograma!J50 -> 0 | H14: =Cronograma!F50+Cronograma!K50 -> 17312.5 | I14: =Cronograma!L50 -> 769.365 | J14: =Cronograma!M50 -> 26414.865 | K14: =Cronograma!N50 -> 35460.135 | L14: =Cronograma!O50 -> 12411.047 | M14: =Cronograma!Q50 -> 4950 | N14: =Cronograma!R50 -> 0 | O14: =Cronograma!S50 -> 18099.088 | P14: =Cronograma!T50 -> 3377688
A15: =Cronograma!C51 -> Dezembro | B15: =Cronograma!D51 -> 0 | C15: =Cronograma!G51 -> 0 | D15: =Cronograma!H51 -> 61875 | E15: =Cronograma!I51 -> 61875 | F15: =Cronograma!E51 -> 8333 | G15: =Cronograma!J51 -> 0 | H15: =Cronograma!F51+Cronograma!K51 -> 17312.5 | I15: =Cronograma!L51 -> 769.365 | J15: =Cronograma!M51 -> 26414.865 | K15: =Cronograma!N51 -> 35460.135 | L15: =Cronograma!O51 -> 12411.047 | M15: =Cronograma!Q51 -> 4950 | N15: =Cronograma!R51 -> 0 | O15: =Cronograma!S51 -> 18099.088 | P15: =Cronograma!T51 -> 3395787.1
A16: TOTAL ANO 4 | B16: =SUM(B4:B15) -> 0 | C16: =SUM(C4:C15) -> 0 | D16: =SUM(D4:D15) -> 742500 | E16: =SUM(E4:E15) -> 742500 | F16: =SUM(F4:F15) -> 99996 | G16: =SUM(G4:G15) -> 0 | H16: =SUM(H4:H15) -> 207750 | I16: =SUM(I4:I15) -> 9232.38 | ... O16: =SUM(O4:O15) -> 217189.05 | P16: =Cronograma!T51 -> 3395787.1
A18: 📌 Todos os valores são fórmulas vinculadas à aba Cronograma, que por sua vez vincula com Parâmetros. Para alterar qualquer premissa, edite apenas a aba Parâmetros.
