Workbook

Sheet Painel Executivo
A1: ESTUDO DE VIABILIDADE — LOTEAMENTO PAPAGAIOS/MG
A2: =Premissas!$B$7&" | 16 ha | "&TEXT(Premissas!$B$17,"#,##0")&" Lotes | "&TEXT(Premissas!$B$22,"R$ #,##0")&"/lote | Abril/2026" -> Urbano — Popular 300m² | 16 ha | 300,0 Lotes | R$ 80000,0/lote | Abril/2026
A3: INDICADOR | B3: VALOR | C3: REFERÊNCIA | D3: STATUS
A4: VGV Total | B4: =Premissas!$B$24 -> 24000000 | C4: — | D4: ✅
A5: VGV Empreendedor (65%) | B5: =Premissas!$B$25 -> 15600000 | C5: — | D5: ✅
A6: Total Custos Operacionais | B6: =Financeiro!$B$12 -> 10013200 | C6: < 70% VGV | D6: ✅
A7: Total Custos (com impostos) | B7: =Financeiro!$B$14 -> 11573200 | C7: — | D7: ✅
A8: Lucro Bruto | B8: =Financeiro!$B$16 -> 13986800 | C8: > 0 | D8: ✅
A9: Margem Bruta (%) | B9: =Financeiro!$C$16 -> 0.58278333 | C9: > 20% | D9: ✅
A10: Lucro Líquido | B10: =Financeiro!$B$17 -> 12426800 | C10: > 0 | D10: ✅
A11: Margem Líquida (%) | B11: =Financeiro!$C$17 -> 0.51778333 | C11: > 15% | D11: ✅
A12: Net Empreendedor (pós-imp. est.) | B12: =Financeiro!$B$19 -> 8077420 | C12: — | D12: ✅
A13: Net Terrenista (35%) | B13: =Financeiro!$B$20 -> 4895380 | C13: — | D13: ✅
A14: Capital próprio | B14: =Premissas!$B$35 -> 1000000 | C14: — | D14: ✅
A15: Payback capital próprio | B15: ~8 meses pós-lançamento | C15: < 48 meses | D15: ✅
A16: Infra total | B16: =Infraestrutura!$E$14 -> 5933200 | C16: — | D16: ✅
A17: Custo infra por lote | B17: =Infraestrutura!$E$15 -> 19777.333 | C17: — | D17: ✅
A18: % Terrenista | B18: =Premissas!$B$20 -> 0.35 | C18: < 40% | D18: ✅
A20: ⚠ PONTOS DE ATENÇÃO
A21: • R$ 4,43M da infraestrutura financiados pelas vendas → exige lançamento forte
A22: • Velocidade de vendas não testada (mercado sem loteamento há +1 ano) → fazer pré-cadastro
A23: • Impostos precisam de validação com contador especializado em loteamento
A24: • Contrato de parceria ainda não assinado → formalizar antes de qualquer custo
A26: ✅ RECOMENDAÇÃO: GO — EMPREENDIMENTO VIÁVEL PARA AVANÇAR

Sheet Premissas
A1: PREMISSAS DO EMPREENDIMENTO — edite aqui e todas as abas recalculam
A2: 🟡 Amarelo = entrada editável | 🔵 Azul claro = calculado automaticamente
A3: A — DADOS DO TERRENO
A4: Área bruta total | B4: 16 | C4: hectares | D4: Informado pelo proprietário
A5: Área bruta total (m²) | B5: =B4*10000 -> 160000 | C5: m² | D5: Calculado
A6: Localização | B6: Papagaios/MG
A7: Tipo de loteamento | B7: Urbano — Popular 300m²
A8: B — PARÂMETROS URBANÍSTICOS (Lei 6.766/79 + Prefeitura Papagaios)
A9: Deduções — Vias públicas (%) | B9: 0.25 | C9: % | D9: Confirmado pela Prefeitura
A10: Deduções — Áreas verdes (%) | B10: 0.1 | C10: % | D10: Mínimo legal
A11: Deduções — Área institucional (%) | B11: 0.08 | C11: % | D11: Confirmado pela Prefeitura
A12: Total de deduções (%) | B12: =B9+B10+B11 -> 0.43 | C12: % | D12: Calculado
A13: Área líquida (%) | B13: =1-B12 -> 0.57 | C13: % | D13: Calculado
A14: Área líquida (m²) | B14: =B5*B13 -> 91200 | C14: m² | D14: Calculado
A15: Tamanho do lote (m²) | B15: 300 | C15: m² | D15: Mínimo definido
A16: Lotes pela área (referência) | B16: =INT(B14/B15) -> 304 | C16: un. | D16: Calculado — somente referência
A17: Lotes aprovados (ajustado) | B17: 300 | C17: un. | D17: ⚠ Ajustado pelo projeto urbanístico — use este valor
A18: C — ESTRUTURA DA PARCERIA
A19: % Empreendedor | B19: 0.65 | D19: Base: lucro líquido antes dos impostos
A20: % Terrenista | B20: =1-B19 -> 0.35 | D20: Calculado
A21: D — COMERCIALIZAÇÃO
A22: Preço de venda por lote (R$) | B22: 80000 | C22: R$ | D22: Referência: último loteamento vendeu a R$75.000
A23: Preço por m² (R$/m²) | B23: =B22/B15 -> 266.66667 | C23: R$/m² | D23: Calculado
A24: VGV Total (R$) | B24: =B17*B22 -> 24000000 | C24: R$ | D24: Calculado
A25: VGV Empreendedor (R$) | B25: =B24*B19 -> 15600000 | C25: R$ | D25: Calculado
A26: VGV Terrenista (R$) | B26: =B24*B20 -> 8400000 | C26: R$ | D26: Calculado
A27: E — TAXAS E PERCENTUAIS
A28: Corretagem (%) | B28: 0.06 | C28: % VGV | D28: Mercado: 5-8%
A29: Marketing e lançamento (%) | B29: 0.02 | C29: % VGV | D29: Referência: 2-3%
A30: Administração (%) | B30: 0.03 | C30: % VGV | D30: Referência: 3-5%
A31: Custo financeiro (%) | B31: 0.03 | C31: % VGV | D31: Capital de giro
A32: Contingência (%) | B32: 0.03 | C32: % VGV | D32: Imprevistos 3-5%
A33: Impostos — Lucro Presumido (%) | B33: 0.065 | C33: % VGV | D33: PIS+COFINS+IRPJ+CSLL — validar com contador
A34: F — CAPITAL E FINANCIAMENTO
A35: Capital próprio disponível (R$) | B35: 1000000 | C35: R$ | D35: Saldo financiado pelas vendas
A36: % lotes à vista / banco | B36: 0.7 | D36: 70% recebido na venda
A37: % lotes financiados (empr.) | B37: =1-B36 -> 0.3 | D37: Calculado
A38: Prazo financiamento (meses) | B38: 60 | C38: meses | D38: Máx. 60 meses
A39: Parcela por lote (R$/mês) | B39: =B22*B37/B38 -> 400 | C39: R$/lote/mês | D39: Calculado
A41: ⚠ Todas as células amarelas são editáveis. As demais são calculadas automaticamente e não devem ser alteradas diretamente.

Sheet Infraestrutura
A1: ORÇAMENTO DE INFRAESTRUTURA — quantities linked to Premissas
A2: 🟡 Custo unitário (col D) = editável | Quantidade (col B) = vínculo com Premissas | Total (col E) = calculado
A3: ITEM | B3: QUANTIDADE | C3: UNIDADE | D3: CUSTO UNIT. (R$) | E3: TOTAL (R$) | F3: OBSERVAÇÃO
A4: Terraplanagem e regularização | B4: =Premissas!$B$5 -> 160000 | C4: m² | D4: 4 | E4: =B4*D4 -> 640000 | F4: R$4/m² — leve declividade
A5: Pavimentação completa (ruas + calçadas + meio-fio) | B5: =Premissas!$B$5*Premissas!$B$9 -> 40000 | C5: m² | D5: 60 | E5: =B5*D5 -> 2400000 | F5: R$60/m² — confirmado pelo usuário
A6: Drenagem pluvial (galerias, bocas-de-lobo) | B6: =Premissas!$B$5*Premissas!$B$9 -> 40000 | C6: m² | D6: 25 | E6: =B6*D6 -> 1000000 | F6: R$20/m²
A7: Rede de abastecimento de água (COPASA) | B7: =Premissas!$B$17 -> 300 | C7: lotes | D7: 1151 | E7: =B7*D7 -> 345300 | F7: R$1.151/lote — ligação à rede
A8: Rede de esgoto (ligação 50m + rede interna) | B8: =Premissas!$B$17 -> 300 | C8: lotes | D8: 1382 | E8: =B8*D8 -> 414600 | F8: Ponto 50m da área mais baixa
A9: Energia elétrica — CEMIG (rede + transformadores) | B9: =Premissas!$B$17 -> 300 | C9: lotes | D9: 1711 | E9: =B9*D9 -> 513300 | F9: R$1.711/lote
A10: Iluminação pública | B10: 140 | C10: pontos | D10: 2500 | E10: =B10*D10 -> 350000 | F10: 140 pontos — R$2.500/ponto
A11: Sinalização, paisagismo e acabamentos | B11: 1 | C11: verba | D11: 120000 | E11: =B11*D11 -> 120000 | F11: Verba global
A12: Projetos urbanísticos e de instalações | B12: 1 | C12: verba | D12: 50000 | E12: =B12*D12 -> 50000 | F12: Orçamento informado
A13: Licenças, cartório, INCRA, aprovações | B13: 1 | C13: verba | D13: 100000 | E13: =B13*D13 -> 100000 | F13: Estimativa
A14: TOTAL GERAL DE INFRAESTRUTURA | E14: =SUM(E4:E13) -> 5933200
A15: Custo de infraestrutura por lote (R$) | E15: =E14/Premissas!$B$17 -> 19777.333

Sheet Financeiro
A1: ANÁLISE FINANCEIRA COMPLETA — 100% fórmulas vinculadas às Premissas
A2: ITEM | B2: VALOR (R$) | C2: % DO VGV | D2: OBSERVAÇÃO
A3: RECEITA
A4: VGV Total (lotes × preço) | B4: =Premissas!$B$24 -> 24000000 | C4: =1 -> 1 | D4: =Premissas!$B$17&" lotes × "&TEXT(Premissas!$B$22,"R$ #,##0") -> 300 lotes × R$ 80000,0
A5: CUSTOS OPERACIONAIS
A6: Infraestrutura total | B6: =Infraestrutura!E14 -> 5933200 | C6: =B6/B4 -> 0.24721667 | D6: Vínculo com aba Infraestrutura
A7: Corretagem | B7: =Premissas!$B$24*Premissas!$B$28 -> 1440000 | C7: =B7/B4 -> 0.06 | D7: =TEXT(Premissas!$B$28,"0%")&" do VGV" -> 6% do VGV
A8: Marketing e lançamento | B8: =Premissas!$B$24*Premissas!$B$29 -> 480000 | C8: =B8/B4 -> 0.02 | D8: =TEXT(Premissas!$B$29,"0%")&" do VGV" -> 2% do VGV
A9: Administração | B9: =Premissas!$B$24*Premissas!$B$30 -> 720000 | C9: =B9/B4 -> 0.03 | D9: =TEXT(Premissas!$B$30,"0%")&" do VGV" -> 3% do VGV
A10: Custo financeiro / capital de giro | B10: =Premissas!$B$24*Premissas!$B$31 -> 720000 | C10: =B10/B4 -> 0.03 | D10: =TEXT(Premissas!$B$31,"0%")&" do VGV" -> 3% do VGV
A11: Contingência | B11: =Premissas!$B$24*Premissas!$B$32 -> 720000 | C11: =B11/B4 -> 0.03 | D11: =TEXT(Premissas!$B$32,"0%")&" do VGV" -> 3% do VGV
A12: TOTAL CUSTOS OPERACIONAIS | B12: =SUM(B6:B11) -> 10013200 | C12: =B12/B4 -> 0.41721667
A13: Impostos estimados — Lucro Presumido | B13: =Premissas!$B$24*Premissas!$B$33 -> 1560000 | C13: =B13/B4 -> 0.065 | D13: =TEXT(Premissas!$B$33,"0.0%")&" do VGV — validar com contador" -> 07% do VGV — validar com contador
A14: TOTAL CUSTOS (com impostos) | B14: =B12+B13 -> 11573200 | C14: =B14/B4 -> 0.48221667
A15: RESULTADOS
A16: Lucro Bruto (antes impostos — base da divisão) | B16: =B4-B12 -> 13986800 | C16: =B16/B4 -> 0.58278333 | D16: Margem Bruta
A17: Lucro Líquido (após impostos) | B17: =B4-B14 -> 12426800 | C17: =B17/B4 -> 0.51778333 | D17: Margem Líquida
A18: DISTRIBUIÇÃO (base = Lucro Bruto antes dos impostos)
A19: Net Empreendedor (65% lucro bruto − impostos do empreendedor) | B19: =B16*Premissas!$B$19 - B13*Premissas!$B$19 -> 8077420 | C19: =B19/B4 -> 0.33655917 | D19: =TEXT(Premissas!$B$19,"0%")&" do lucro − proporcional dos impostos" -> 65% do lucro − proporcional dos impostos
A20: Net Terrenista (35% do lucro bruto) | B20: =B16*Premissas!$B$20 -> 4895380 | C20: =B20/B4 -> 0.20397417 | D20: =TEXT(Premissas!$B$20,"0%")&" do lucro bruto" -> 35% do lucro bruto
A21: PAYBACK DO CAPITAL PRÓPRIO
A22: Capital próprio disponível | B22: =Premissas!$B$35 -> 1000000 | D22: Vínculo com Premissas!B35
A23: Receita média mensal esperada (12 lotes/mês) | B23: =12*Premissas!$B$22 -> 960000 | D23: 12 lotes/mês × preço
A24: Payback estimado do capital próprio (meses) | B24: ~8 meses | D24: ~8 meses pós-lançamento

Sheet Cenários
A1: ANÁLISE DE CENÁRIOS — Preço e Velocidade de Vendas
A2: Linha 3 (preço) é editável nos cenários pessimista e otimista. Moderado víncula com Premissas automaticamente.
A3: INDICADOR | B3: PESSIMISTA | C3: MODERADO ★ BASE | D3: OTIMISTA
A4: Preço de venda por lote (R$) | B4: 65000 | C4: =Premissas!$B$22 -> 80000 | D4: 95000
A5: Velocidade de vendas (lotes/mês) | B5: 6 | C5: 12 | D5: 18
A6: Número de lotes | B6: =Premissas!$B$17 -> 300 | C6: =Premissas!$B$17 -> 300 | D6: =Premissas!$B$17 -> 300
A7: VGV Total (R$) | B7: =B4*B6 -> 19500000 | C7: =C4*C6 -> 24000000 | D7: =D4*D6 -> 28500000
A8: Custos operacionais estimados (R$) | B8: =Infraestrutura!$E$14+B8*(Premissas!$B$28+Premissas!$B$29+Premissas!$B$30+Premissas!$B$31+Premissas!$B$32) | C8: =Infraestrutura!$E$14+C8*(Premissas!$B$28+Premissas!$B$29+Premissas!$B$30+Premissas!$B$31+Premissas!$B$32) | D8: =Infraestrutura!$E$14+D8*(Premissas!$B$28+Premissas!$B$29+Premissas!$B$30+Premissas!$B$31+Premissas!$B$32)
A9: Lucro Bruto (R$) | B9: =B8-B9 | C9: =C8-C9 | D9: =D8-D9
A10: Margem Bruta (%) | B10: =B10/B8 | C10: =C10/C8 | D10: =D10/D8
A11: Net Empreendedor 65% (R$) | B11: =B10*Premissas!$B$19 | C11: =C10*Premissas!$B$19 | D11: =D10*Premissas!$B$19
A12: Meses para vender tudo | B12: =Premissas!$B$17/B6 -> 1 | C12: =Premissas!$B$17/C6 -> 1 | D12: =Premissas!$B$17/D6 -> 1
