Workbook

Sheet Painel Executivo
A1: ESTUDO DE VIABILIDADE ECONÔMICA — LOTEAMENTO PAPAGAIOS/MG
A2: Abril/2026 | Loteamento Popular | 16 ha | 304 Lotes | R$ 75.000/lote
A4: INDICADOR | B4: VALOR | C4: REFERÊNCIA | D4: STATUS
A5: VGV Total | B5: ='Premissas'!B5 | C5: — | D5: ✅
A6: VGV Empreendedor (65%) | B6: ='Financeiro'!B22 | C6: — | D6: ✅
A7: Custo Total (com impostos) | B7: ='Financeiro'!B18 | C7: < 70% VGV | D7: ✅
A8: Lucro Bruto (antes impostos) | B8: ='Financeiro'!B19 | C8: — | D8: ✅
A9: Margem Bruta | B9: ='Financeiro'!C19 | C9: > 20% | D9: ✅
A10: Lucro Líquido Estimado | B10: ='Financeiro'!B20 | C10: — | D10: ✅
A11: Margem Líquida | B11: ='Financeiro'!C20 | C11: > 15% | D11: ✅
A12: Net Empreendedor (pós-impostos) | B12: ='Financeiro'!B23 | C12: — | D12: ✅
A13: Net Terrenista (35%) | B13: ='Financeiro'!B24 | C13: — | D13: ✅
A14: Payback Capital Próprio | B14: ='Financeiro'!B28 | C14: < 48 meses | D14: ✅
A15: VPL (TMA 12% a.a.) | B15: ='Fluxo_Caixa'!B25 | C15: > 0 | D15: ✅
A16: TIR estimada | B16: ='Fluxo_Caixa'!B26 | C16: > 12% a.a. | D16: ✅
A18: ⚠️ PONTOS DE ATENÇÃO
A19: • R$ 4,43M de infraestrutura financiada pelas vendas → exige vendas fortes no lançamento
A20: • Velocidade de vendas não testada (mercado parado há +1 ano) → recomendado pré-cadastro antes do lançamento
A21: • Impostos precisam de validação com contador especializado em loteamento
A22: • Contrato de parceria ainda não assinado → formalizar antes de qualquer custo
A24: ✅ RECOMENDAÇÃO: GO — EMPREENDIMENTO VIÁVEL PARA AVANÇAR

Sheet Premissas
A1: PREMISSAS DO EMPREENDIMENTO
A2: DADOS DO TERRENO
A3: Área bruta total (ha) | B3: 16 | C3: ha
A4: Área bruta total (m²) | B4: =B2*10000 | C4: m²
A5: Localização | B5: Papagaios/MG
A6: Tipo | B6: Urbano — Loteamento Popular
A7: Restrições conhecidas | B7: Nenhuma
A8: Zoneamento | B8: Zona Urbana
A10: PARÂMETROS URBANÍSTICOS (Lei 6.766/79)
A11: Deduções — Vias públicas (%) | B11: 0.25 | C11: %
A12: Deduções — Áreas verdes (%) | B12: 0.1 | C12: %
A13: Deduções — Área institucional (%) | B13: 0.08 | C13: %
A14: Total de deduções (%) | B14: =B9+B10+B11 | C14: %
A15: Área líquida (%) | B15: =1-B12 | C15: %
A16: Área líquida (m²) | B16: =B4*B13 | C16: m²
A17: Tamanho do lote (m²) | B17: 300 | C17: m²
A18: Número de lotes | B18: =INT(B14/B15) | C18: unidades
A20: PARCERIA E COMERCIALIZAÇÃO
A21: Modelo | B21: Permuta financeira
A22: % Empreendedor | B22: 0.65 | C22: %
A23: % Terrenista | B23: 0.35 | C23: %
A24: Preço de venda por lote (R$) | B24: 75000 | C24: R$
A25: Preço por m² (R$) | B25: =B21/B15 | C25: R$/m²
A26: VGV Total (R$) | B26: =B16*B21 | C26: R$
A27: VGV Empreendedor (R$) | B27: =B23*B18 | C27: R$
A28: VGV Terrenista (R$) | B28: =B23*B19 | C28: R$

Sheet Financeiro
A1: ANÁLISE FINANCEIRA — CUSTOS, RECEITAS E DISTRIBUIÇÃO
A2: ITEM | B2: VALOR (R$) | C2: % DO VGV | D2: OBSERVAÇÃO
A3: RECEITA
A4: VGV Total (304 lotes × R$ 75.000) | B4: =Premissas!B23 | C4: 1 | D4: Premissas!B23
A5: CUSTOS DO EMPREENDIMENTO
A6: Infraestrutura — Terraplanagem (R$ 4/m² × 160.000 m²) | B6: 640000 | C6: =B6/B4 | D6: Leve declividade
A7: Infraestrutura — Pavimentação completa (R$ 60/m² × 40.000 m²) | B7: 2400000 | C7: =B7/B4 | D7: Usuário confirmou R$ 60/m²
A8: Infraestrutura — Drenagem pluvial (R$ 20/m² × 40.000 m²) | B8: 480000 | C8: =B8/B4 | D8: Galerias e bocas-de-lobo
A9: Infraestrutura — Rede de água (COPASA, 304 lotes) | B9: 350000 | C9: =B9/B4 | D9: R$ 1.151/lote
A10: Infraestrutura — Rede de esgoto (50m + rede interna) | B10: 420000 | C10: =B10/B4 | D10: R$ 1.382/lote
A11: Infraestrutura — Energia elétrica CEMIG | B11: 520000 | C11: =B11/B4 | D11: R$ 1.711/lote
A12: Infraestrutura — Iluminação pública (140 pontos) | B12: 350000 | C12: =B12/B4 | D12: R$ 2.500/ponto
A13: Infraestrutura — Sinalização e acabamentos | B13: 120000 | C13: =B13/B4 | D13: Verba
A14: Projetos urbanísticos e instalações | B14: 50000 | C14: =B14/B4 | D14: Orçamento informado
A15: Licenças, cartório, INCRA, aprovações | B15: 100000 | C15: =B15/B4 | D15: Estimativa
A16: Corretagem (6% do VGV) | B16: =B4*0.06 | C16: =B16/B4 | D16: 6% sobre VGV
A17: Marketing e lançamento (2% do VGV) | B17: =B4*0.02 | C17: =B17/B4 | D17: 2% sobre VGV
A18: Administração (3% do VGV) | B18: =B4*0.03 | C18: =B18/B4 | D18: 3% sobre VGV
A19: Custo financeiro / capital de giro (3% do VGV) | B19: =B4*0.03 | C19: =B19/B4 | D19: 3% sobre VGV
A20: Contingência (3% do VGV) | B20: =B4*0.03 | C20: =B20/B4 | D20: 3% sobre VGV
A21: TOTAL CUSTOS OPERACIONAIS | B21: =SUM(B6:B20) | C21: =B21/B4
A22: Impostos estimados — Lucro Presumido (~6,5% VGV) | B22: =B4*0.065 | C22: =B22/B4 | D22: PIS+COFINS+IRPJ+CSLL — validar com contador
A23: TOTAL CUSTOS (com impostos) | B23: =B21+B22 | C23: =B23/B4
A24: RESULTADOS
A25: Lucro Bruto (antes impostos) | B25: =B4-B21 | C25: =B25/B4 | D25: Margem Bruta
A26: Lucro Líquido (após impostos) | B26: =B4-B23 | C26: =B26/B4 | D26: Margem Líquida
A27: DISTRIBUIÇÃO (base = Lucro antes impostos)
A28: Net Empreendedor (65% do lucro bruto — impostos) | B28: =B25*Premissas!B18-B22*Premissas!B18
A29: Net Terrenista (35% do lucro bruto) | B29: =B25*Premissas!B19
A30: PAYBACK
A31: Capital próprio disponível (R$) | B31: 1000000 | C31: Informado pelo investidor
A32: Payback do capital próprio (meses estimados) | B32: 8 | C32: Estimativa: ~6-9 meses pós-lançamento

Sheet Fluxo_Caixa
A1: FLUXO DE CAIXA — PERSPECTIVA DO EMPREENDEDOR (Simplificado)
A2: ITEM | B2: ANO 0 | C2: ANO 1 | D2: ANO 2 | E2: ANO 3 | F2: ANO 4
A3: Receita de vendas (65% VGV) | B3: 0 | C3: 3510000 | D3: 7410000 | E3: 7410000 | F3: 4470000
A4: (-) Infraestrutura e obras | B4: -500000 | C4: -2000000 | D4: -1800000 | E4: -900000 | F4: -230000
A5: (-) Custos comerciais e admin | B5: 0 | C5: -760000 | D5: -1014000 | E5: -785000 | F5: -405000
A6: (-) Pagamento terrenista (35%) | B6: 0 | C6: -1012500 | D6: -2137500 | E6: -2137500 | F6: -1287500
A7: (-) Impostos | B7: 0 | C7: -228150 | D7: -481950 | E7: -481950 | F7: -290850
A8: (-) Capital próprio investido | B8: -1000000 | C8: 0 | D8: 0 | E8: 0 | F8: 0
A9: FLUXO LÍQUIDO DO EMPREENDEDOR | B9: -1500000 | C9: -490150 | D9: 1976550 | E9: 3105550 | F9: 2256650
A10: FLUXO ACUMULADO | B10: -1500000 | C10: -1990150 | D10: -13600 | E10: 3091950 | F10: 5348600
A12: TMA (Taxa Mínima de Atratividade) | B12: 0.12 | C12: 12% a.a. (referência de mercado)
A13: VPL — Valor Presente Líquido | B13: =NPV(B12,C9:F9)+B9 | C13: VPL > 0 confirma viabilidade
A14: TIR — Taxa Interna de Retorno | B14: =IRR(B9:F9) | C14: TIR >> TMA = excelente retorno
A16: ⚠ TIR alta reflete alavancagem do capital próprio (R$ 1M) com restante financiado pelas vendas. Ajuste os fluxos de caixa conforme evolução real das vendas.

Sheet Cenários
A1: ANÁLISE DE CENÁRIOS — PREÇO DE VENDA vs VELOCIDADE DE VENDAS
A2: INDICADOR | B2: PESSIMISTA | C2: MODERADO | D2: OTIMISTA
A3: Preço de venda por lote (R$) | B3: 60000 | C3: 75000 | D3: 90000
A4: Velocidade de vendas (lotes/mês) | B4: 6 | C4: 12 | D4: 18
A5: VGV Total (R$) | B5: =B3*304 | C5: =C3*304 | D5: =D3*304
A6: Custo Total estimado (R$) | B6: 9306000 | C6: 9306000 | D6: 9306000
A7: Lucro Bruto (R$) | B7: =B5-B6 | C7: =C5-C6 | D7: =D5-D6
A8: Margem Bruta (%) | B8: =B7/B5 | C8: =C7/C5 | D8: =D7/D5
A9: Net Empreendedor 65% (R$) | B9: =B7*0.65 | C9: =C7*0.65 | D9: =D7*0.65
A10: Meses para vender tudo | B10: =304/B4 | C10: =304/C4 | D10: =304/D4

Sheet Infraestrutura
A1: ORÇAMENTO DE INFRAESTRUTURA — LOTEAMENTO PAPAGAIOS/MG
A2: ITEM | B2: QUANTIDADE | C2: UNIDADE | D2: UNIT (R$) | E2: TOTAL (R$)
A3: Terraplanagem e regularização | B3: 160.000 | C3: m² | D3: 4 | E3: =D3*160000
A4: Pavimentação completa (ruas + calçadas + meio-fio) | B4: 40.000 | C4: m² | D4: 60 | E4: =D4*40000
A5: Drenagem pluvial (galerias, bocas-de-lobo) | B5: 40.000 | C5: m² | D5: 20 | E5: =D5*40000
A6: Rede de abastecimento de água (COPASA) | B6: 304 | C6: lotes | D6: 1151 | E6: =D6*304
A7: Rede de esgoto (ligação 50m + rede interna) | B7: 304 | C7: lotes | D7: 1382 | E7: =D7*304
A8: Energia elétrica — CEMIG (rede + transformadores) | B8: 304 | C8: lotes | D8: 1711 | E8: =D8*304
A9: Iluminação pública | B9: 140 | C9: pontos | D9: 2500 | E9: =D9*140
A10: Sinalização, paisagismo e acabamentos | B10: 1 | C10: verba | D10: 120000 | E10: =D10*1
A11: Projetos urbanísticos e de instalações | B11: 1 | C11: verba | D11: 50000 | E11: =D11*1
A12: Licenças, cartório, INCRA, aprovações | B12: 1 | C12: verba | D12: 100000 | E12: =D12*1
A13: TOTAL GERAL DE INFRAESTRUTURA | E13: =SUM(E3:E12)
A14: Custo por lote (R$) | E14: =E13/304
